Workbook

Sheet Калькулятор инвестора
B1: LUCE SILVA — КАЛЬКУЛЯТОР ДОХОДНОСТИ ИНВЕСТОРА
B2: Введите сумму — и увидите свой доход в 2027, 2028, 2029 году и стоимость доли при продаже
B4: ВАШ ВКЛАД В ПРОЕКТ | C4: МИН (80 свадеб) | D4: БАЗОВЫЙ (100) | E4: МАКС (150)
B5: 💰 Ваша сумма инвестиций | C5: 1000000 | D5: ← МЕНЯЙТЕ ЭТУ ЯЧЕЙКУ
B6: Ваша доля в проекте | C6: =C5/Допущения!C5*Допущения!C6 -> 0.0074242424
B7: Ваша доля в пуле инвесторов (от 66 млн ₽) | C7: =C5/Допущения!C5 -> 0.015151515
B8: Минимальный чек входа в раунд | C8: =Допущения!C8 -> 1000000
B10: ПОКАЗАТЕЛЬ | C10: 📉 МИНИМАЛЬНЫЙ 80 свадеб | D10: 📊 БАЗОВЫЙ 100 свадеб | E10: 📈 МАКСИМАЛЬНЫЙ 120 свадеб
B11: ДИВИДЕНДНЫЙ ДОХОД ПО ГОДАМ — ВАШ ЛИЧНЫЙ РАСЧЁТ
B13: 📅 2027 год — первый сезон (май–октябрь) | C13: Механика: 80% прибыли | D13: Механика: 80% прибыли | E13: Механика: 80% прибыли
B14: Прибыль проекта за сезон | C14: =Сценарии!C7 -> 52.72 | D14: =Сценарии!D7 -> 65.9 | E14: =Сценарии!E7 -> 79.08
B15: Пул дивидендов (80% → все инвесторы) | C15: =Сценарии!C8 -> 42.176 | D15: =Сценарии!D8 -> 52.72 | E15: =Сценарии!E8 -> 63.264
B16: 💵 Ваш доход в 2029 году | C16: =Сценарии!C7*1000000*Допущения!C7*(C5/Допущения!C5) -> 639030.3 | D16: =Сценарии!D7*1000000*Допущения!C7*(C5/Допущения!C5) -> 798787.88 | E16: =Сценарии!E7*1000000*Допущения!C7*(C5/Допущения!C5) -> 958545.45
B17: Доходность за год | C17: =(Сценарии!C7*1000000*Допущения!C7*(C5/Допущения!C5))/C5 -> 0.6390303 | D17: =(Сценарии!D7*1000000*Допущения!C7*(C5/Допущения!C5))/C5 -> 0.79878788 | E17: =(Сценарии!E7*1000000*Допущения!C7*(C5/Допущения!C5))/C5 -> 0.95854545
B19: 📅 2028 год — второй сезон (май–октябрь) | C19: 80% (ещё в возврате) | D19: 80%→49% (переход) | E19: 49% (возврат завершён)
B20: Прибыль проекта за сезон | C20: =Сценарии!C7 -> 52.72 | D20: =Сценарии!D7 -> 65.9 | E20: =Сценарии!E7 -> 79.08
B21: 💵 Ваш доход в 2027 году | C21: =IF(MAX(0,Допущения!C5-Сценарии!C7*1000000*Допущения!C7)=0,Сценарии!C7*1000000*Допущения!C6,IF(MAX(0,Допущения!C5-Сценарии!C7*1000000*Допущения!C7)>=Сценарии!C7*1000000*Допущения!C7,Сценарии!C7*1000000*Допущения!C7,MAX(0,Допущения!C5-Сценарии!C7*1000000*Допущения!C7)+(Сценарии!C7*1000000-MAX(0,Допущения!C5-Сценарии!C7*1000000*Допущения!C7)/Допущения!C7)*Допущения!C6))*(C5/Допущения!C5) -> 531281.82 | D21: =IF(MAX(0,Допущения!C5-Сценарии!D7*1000000*Допущения!C7)=0,Сценарии!D7*1000000*Допущения!C6,IF(MAX(0,Допущения!C5-Сценарии!D7*1000000*Допущения!C7)>=Сценарии!D7*1000000*Допущения!C7,Сценарии!D7*1000000*Допущения!C7,MAX(0,Допущения!C5-Сценарии!D7*1000000*Допущения!C7)+(Сценарии!D7*1000000-MAX(0,Допущения!C5-Сценарии!D7*1000000*Допущения!C7)/Допущения!C7)*Допущения!C6))*(C5/Допущения!C5) -> 567227.27 | E21: =IF(MAX(0,Допущения!C5-Сценарии!E7*1000000*Допущения!C7)=0,Сценарии!E7*1000000*Допущения!C6,IF(MAX(0,Допущения!C5-Сценарии!E7*1000000*Допущения!C7)>=Сценарии!E7*1000000*Допущения!C7,Сценарии!E7*1000000*Допущения!C7,MAX(0,Допущения!C5-Сценарии!E7*1000000*Допущения!C7)+(Сценарии!E7*1000000-MAX(0,Допущения!C5-Сценарии!E7*1000000*Допущения!C7)/Допущения!C7)*Допущения!C6))*(C5/Допущения!C5) -> 603172.73
B22: Доходность за год | C22: =(IF(MAX(0,Допущения!C5-Сценарии!C7*1000000*Допущения!C7)=0,Сценарии!C7*1000000*Допущения!C6,IF(MAX(0,Допущения!C5-Сценарии!C7*1000000*Допущения!C7)>=Сценарии!C7*1000000*Допущения!C7,Сценарии!C7*1000000*Допущения!C7,MAX(0,Допущения!C5-Сценарии!C7*1000000*Допущения!C7)+(Сценарии!C7*1000000-MAX(0,Допущения!C5-Сценарии!C7*1000000*Допущения!C7)/Допущения!C7)*Допущения!C6))*(C5/Допущения!C5))/C5 -> 0.53128182 | D22: =(IF(MAX(0,Допущения!C5-Сценарии!D7*1000000*Допущения!C7)=0,Сценарии!D7*1000000*Допущения!C6,IF(MAX(0,Допущения!C5-Сценарии!D7*1000000*Допущения!C7)>=Сценарии!D7*1000000*Допущения!C7,Сценарии!D7*1000000*Допущения!C7,MAX(0,Допущения!C5-Сценарии!D7*1000000*Допущения!C7)+(Сценарии!D7*1000000-MAX(0,Допущения!C5-Сценарии!D7*1000000*Допущения!C7)/Допущения!C7)*Допущения!C6))*(C5/Допущения!C5))/C5 -> 0.56722727 | E22: =(IF(MAX(0,Допущения!C5-Сценарии!E7*1000000*Допущения!C7)=0,Сценарии!E7*1000000*Допущения!C6,IF(MAX(0,Допущения!C5-Сценарии!E7*1000000*Допущения!C7)>=Сценарии!E7*1000000*Допущения!C7,Сценарии!E7*1000000*Допущения!C7,MAX(0,Допущения!C5-Сценарии!E7*1000000*Допущения!C7)+(Сценарии!E7*1000000-MAX(0,Допущения!C5-Сценарии!E7*1000000*Допущения!C7)/Допущения!C7)*Допущения!C6))*(C5/Допущения!C5))/C5 -> 0.60317273
B24: 📅 2029 год — третий сезон (май–октябрь) | C24: 80%/49% (переход) | D24: 49% (стабильно) | E24: 49% (стабильно)
B25: Прибыль проекта за сезон | C25: =Сценарии!C7 -> 52.72 | D25: =Сценарии!D7 -> 65.9 | E25: =Сценарии!E7 -> 79.08
B26: 💵 Ваш доход в 2028 году | C26: =IF(MAX(0,MAX(0,Допущения!C5-Сценарии!C7*1000000*Допущения!C7)-IF(MAX(0,Допущения!C5-Сценарии!C7*1000000*Допущения!C7)=0,Сценарии!C7*1000000*Допущения!C6,IF(MAX(0,Допущения!C5-Сценарии!C7*1000000*Допущения!C7)>=Сценарии!C7*1000000*Допущения!C7,Сценарии!C7*1000000*Допущения!C7,MAX(0,Допущения!C5-Сценарии!C7*1000000*Допущения!C7)+(Сценарии!C7*1000000-MAX(0,Допущения!C5-Сценарии!C7*1000000*Допущения!C7)/Допущения!C7)*Допущения!C6)))=0,Сценарии!C7*1000000*Допущения!C6,IF(MAX(0,MAX(0,Допущения!C5-Сценарии!C7*1000000*Допущения!C7)-IF(MAX(0,Допущения!C5-Сценарии!C7*1000000*Допущения!C7)=0,Сценарии!C7*1000000*Допущения!C6,IF(MAX(0,Допущения!C5-Сценарии!C7*1000000*Допущения!C7)>=Сценарии!C7*1000000*Допущения!C7,Сценарии!C7*1000000*Допущения!C7,MAX(0,Допущения!C5-Сценарии!C7*1000000*Допущения!C7)+(Сценарии!C7*1000000-MAX(0,Допущения!C5-Сценарии!C7*1000000*Допущения!C7)/Допущения!C7)*Допущения!C6)))>=Сценарии!C7*1000000*Допущения!C7,Сценарии!C7*1000000*Допущения!C7,MAX(0,MAX(0,Допущения!C5-Сценарии!C7*1000000*Допущения!C7)-IF(MAX(0,Допущения!C5-Сценарии!C7*1000000*Допущения!C7)=0,Сценарии!C7*1000000*Допущения!C6,IF(MAX(0,Допущения!C5-Сценарии!C7*1000000*Допущения!C7)>=Сценарии!C7*1000000*Допущения!C7,Сценарии!C7*1000000*Допущения!C7,MAX(0,Допущения!C5-Сценарии!C7*1000000*Допущения!C7)+(Сценарии!C7*1000000-MAX(0,Допущения!C5-Сценарии!C7*1000000*Допущения!C7)/Допущения!C7)*Допущения!C6)))+(Сценарии!C7*1000000-MAX(0,MAX(0,Допущения!C5-Сценарии!C7*1000000*Допущения!C7)-IF(MAX(0,Допущения!C5-Сценарии!C7*1000000*Допущения!C7)=0,Сценарии!C7*1000000*Допущения!C6,IF(MAX(0,Допущения!C5-Сценарии!C7*1000000*Допущения!C7)>=Сценарии!C7*1000000*Допущения!C7,Сценарии!C7*1000000*Допущения!C7,MAX(0,Допущения!C5-Сценарии!C7*1000000*Допущения!C7)+(Сценарии!C7*1000000-MAX(0,Допущения!C5-Сценарии!C7*1000000*Допущения!C7)/Допущения!C7)*Допущения!C6)))/Допущения!C7)*Допущения!C6))*(C5/Допущения!C5) -> 391406.06 | D26: =IF(MAX(0,MAX(0,Допущения!C5-Сценарии!D7*1000000*Допущения!C7)-IF(MAX(0,Допущения!C5-Сценарии!D7*1000000*Допущения!C7)=0,Сценарии!D7*1000000*Допущения!C6,IF(MAX(0,Допущения!C5-Сценарии!D7*1000000*Допущения!C7)>=Сценарии!D7*1000000*Допущения!C7,Сценарии!D7*1000000*Допущения!C7,MAX(0,Допущения!C5-Сценарии!D7*1000000*Допущения!C7)+(Сценарии!D7*1000000-MAX(0,Допущения!C5-Сценарии!D7*1000000*Допущения!C7)/Допущения!C7)*Допущения!C6)))=0,Сценарии!D7*1000000*Допущения!C6,IF(MAX(0,MAX(0,Допущения!C5-Сценарии!D7*1000000*Допущения!C7)-IF(MAX(0,Допущения!C5-Сценарии!D7*1000000*Допущения!C7)=0,Сценарии!D7*1000000*Допущения!C6,IF(MAX(0,Допущения!C5-Сценарии!D7*1000000*Допущения!C7)>=Сценарии!D7*1000000*Допущения!C7,Сценарии!D7*1000000*Допущения!C7,MAX(0,Допущения!C5-Сценарии!D7*1000000*Допущения!C7)+(Сценарии!D7*1000000-MAX(0,Допущения!C5-Сценарии!D7*1000000*Допущения!C7)/Допущения!C7)*Допущения!C6)))>=Сценарии!D7*1000000*Допущения!C7,Сценарии!D7*1000000*Допущения!C7,MAX(0,MAX(0,Допущения!C5-Сценарии!D7*1000000*Допущения!C7)-IF(MAX(0,Допущения!C5-Сценарии!D7*1000000*Допущения!C7)=0,Сценарии!D7*1000000*Допущения!C6,IF(MAX(0,Допущения!C5-Сценарии!D7*1000000*Допущения!C7)>=Сценарии!D7*1000000*Допущения!C7,Сценарии!D7*1000000*Допущения!C7,MAX(0,Допущения!C5-Сценарии!D7*1000000*Допущения!C7)+(Сценарии!D7*1000000-MAX(0,Допущения!C5-Сценарии!D7*1000000*Допущения!C7)/Допущения!C7)*Допущения!C6)))+(Сценарии!D7*1000000-MAX(0,MAX(0,Допущения!C5-Сценарии!D7*1000000*Допущения!C7)-IF(MAX(0,Допущения!C5-Сценарии!D7*1000000*Допущения!C7)=0,Сценарии!D7*1000000*Допущения!C6,IF(MAX(0,Допущения!C5-Сценарии!D7*1000000*Допущения!C7)>=Сценарии!D7*1000000*Допущения!C7,Сценарии!D7*1000000*Допущения!C7,MAX(0,Допущения!C5-Сценарии!D7*1000000*Допущения!C7)+(Сценарии!D7*1000000-MAX(0,Допущения!C5-Сценарии!D7*1000000*Допущения!C7)/Допущения!C7)*Допущения!C6)))/Допущения!C7)*Допущения!C6))*(C5/Допущения!C5) -> 489257.58 | E26: =IF(MAX(0,MAX(0,Допущения!C5-Сценарии!E7*1000000*Допущения!C7)-IF(MAX(0,Допущения!C5-Сценарии!E7*1000000*Допущения!C7)=0,Сценарии!E7*1000000*Допущения!C6,IF(MAX(0,Допущения!C5-Сценарии!E7*1000000*Допущения!C7)>=Сценарии!E7*1000000*Допущения!C7,Сценарии!E7*1000000*Допущения!C7,MAX(0,Допущения!C5-Сценарии!E7*1000000*Допущения!C7)+(Сценарии!E7*1000000-MAX(0,Допущения!C5-Сценарии!E7*1000000*Допущения!C7)/Допущения!C7)*Допущения!C6)))=0,Сценарии!E7*1000000*Допущения!C6,IF(MAX(0,MAX(0,Допущения!C5-Сценарии!E7*1000000*Допущения!C7)-IF(MAX(0,Допущения!C5-Сценарии!E7*1000000*Допущения!C7)=0,Сценарии!E7*1000000*Допущения!C6,IF(MAX(0,Допущения!C5-Сценарии!E7*1000000*Допущения!C7)>=Сценарии!E7*1000000*Допущения!C7,Сценарии!E7*1000000*Допущения!C7,MAX(0,Допущения!C5-Сценарии!E7*1000000*Допущения!C7)+(Сценарии!E7*1000000-MAX(0,Допущения!C5-Сценарии!E7*1000000*Допущения!C7)/Допущения!C7)*Допущения!C6)))>=Сценарии!E7*1000000*Допущения!C7,Сценарии!E7*1000000*Допущения!C7,MAX(0,MAX(0,Допущения!C5-Сценарии!E7*1000000*Допущения!C7)-IF(MAX(0,Допущения!C5-Сценарии!E7*1000000*Допущения!C7)=0,Сценарии!E7*1000000*Допущения!C6,IF(MAX(0,Допущения!C5-Сценарии!E7*1000000*Допущения!C7)>=Сценарии!E7*1000000*Допущения!C7,Сценарии!E7*1000000*Допущения!C7,MAX(0,Допущения!C5-Сценарии!E7*1000000*Допущения!C7)+(Сценарии!E7*1000000-MAX(0,Допущения!C5-Сценарии!E7*1000000*Допущения!C7)/Допущения!C7)*Допущения!C6)))+(Сценарии!E7*1000000-MAX(0,MAX(0,Допущения!C5-Сценарии!E7*1000000*Допущения!C7)-IF(MAX(0,Допущения!C5-Сценарии!E7*1000000*Допущения!C7)=0,Сценарии!E7*1000000*Допущения!C6,IF(MAX(0,Допущения!C5-Сценарии!E7*1000000*Допущения!C7)>=Сценарии!E7*1000000*Допущения!C7,Сценарии!E7*1000000*Допущения!C7,MAX(0,Допущения!C5-Сценарии!E7*1000000*Допущения!C7)+(Сценарии!E7*1000000-MAX(0,Допущения!C5-Сценарии!E7*1000000*Допущения!C7)/Допущения!C7)*Допущения!C6)))/Допущения!C7)*Допущения!C6))*(C5/Допущения!C5) -> 587109.09
B27: Доходность за год | C27: =(IF(MAX(0,MAX(0,Допущения!C5-Сценарии!C7*1000000*Допущения!C7)-IF(MAX(0,Допущения!C5-Сценарии!C7*1000000*Допущения!C7)=0,Сценарии!C7*1000000*Допущения!C6,IF(MAX(0,Допущения!C5-Сценарии!C7*1000000*Допущения!C7)>=Сценарии!C7*1000000*Допущения!C7,Сценарии!C7*1000000*Допущения!C7,MAX(0,Допущения!C5-Сценарии!C7*1000000*Допущения!C7)+(Сценарии!C7*1000000-MAX(0,Допущения!C5-Сценарии!C7*1000000*Допущения!C7)/Допущения!C7)*Допущения!C6)))=0,Сценарии!C7*1000000*Допущения!C6,IF(MAX(0,MAX(0,Допущения!C5-Сценарии!C7*1000000*Допущения!C7)-IF(MAX(0,Допущения!C5-Сценарии!C7*1000000*Допущения!C7)=0,Сценарии!C7*1000000*Допущения!C6,IF(MAX(0,Допущения!C5-Сценарии!C7*1000000*Допущения!C7)>=Сценарии!C7*1000000*Допущения!C7,Сценарии!C7*1000000*Допущения!C7,MAX(0,Допущения!C5-Сценарии!C7*1000000*Допущения!C7)+(Сценарии!C7*1000000-MAX(0,Допущения!C5-Сценарии!C7*1000000*Допущения!C7)/Допущения!C7)*Допущения!C6)))>=Сценарии!C7*1000000*Допущения!C7,Сценарии!C7*1000000*Допущения!C7,MAX(0,MAX(0,Допущения!C5-Сценарии!C7*1000000*Допущения!C7)-IF(MAX(0,Допущения!C5-Сценарии!C7*1000000*Допущения!C7)=0,Сценарии!C7*1000000*Допущения!C6,IF(MAX(0,Допущения!C5-Сценарии!C7*1000000*Допущения!C7)>=Сценарии!C7*1000000*Допущения!C7,Сценарии!C7*1000000*Допущения!C7,MAX(0,Допущения!C5-Сценарии!C7*1000000*Допущения!C7)+(Сценарии!C7*1000000-MAX(0,Допущения!C5-Сценарии!C7*1000000*Допущения!C7)/Допущения!C7)*Допущения!C6)))+(Сценарии!C7*1000000-MAX(0,MAX(0,Допущения!C5-Сценарии!C7*1000000*Допущения!C7)-IF(MAX(0,Допущения!C5-Сценарии!C7*1000000*Допущения!C7)=0,Сценарии!C7*1000000*Допущения!C6,IF(MAX(0,Допущения!C5-Сценарии!C7*1000000*Допущения!C7)>=Сценарии!C7*1000000*Допущения!C7,Сценарии!C7*1000000*Допущения!C7,MAX(0,Допущения!C5-Сценарии!C7*1000000*Допущения!C7)+(Сценарии!C7*1000000-MAX(0,Допущения!C5-Сценарии!C7*1000000*Допущения!C7)/Допущения!C7)*Допущения!C6)))/Допущения!C7)*Допущения!C6))*(C5/Допущения!C5))/C5 -> 0.39140606 | D27: =(IF(MAX(0,MAX(0,Допущения!C5-Сценарии!D7*1000000*Допущения!C7)-IF(MAX(0,Допущения!C5-Сценарии!D7*1000000*Допущения!C7)=0,Сценарии!D7*1000000*Допущения!C6,IF(MAX(0,Допущения!C5-Сценарии!D7*1000000*Допущения!C7)>=Сценарии!D7*1000000*Допущения!C7,Сценарии!D7*1000000*Допущения!C7,MAX(0,Допущения!C5-Сценарии!D7*1000000*Допущения!C7)+(Сценарии!D7*1000000-MAX(0,Допущения!C5-Сценарии!D7*1000000*Допущения!C7)/Допущения!C7)*Допущения!C6)))=0,Сценарии!D7*1000000*Допущения!C6,IF(MAX(0,MAX(0,Допущения!C5-Сценарии!D7*1000000*Допущения!C7)-IF(MAX(0,Допущения!C5-Сценарии!D7*1000000*Допущения!C7)=0,Сценарии!D7*1000000*Допущения!C6,IF(MAX(0,Допущения!C5-Сценарии!D7*1000000*Допущения!C7)>=Сценарии!D7*1000000*Допущения!C7,Сценарии!D7*1000000*Допущения!C7,MAX(0,Допущения!C5-Сценарии!D7*1000000*Допущения!C7)+(Сценарии!D7*1000000-MAX(0,Допущения!C5-Сценарии!D7*1000000*Допущения!C7)/Допущения!C7)*Допущения!C6)))>=Сценарии!D7*1000000*Допущения!C7,Сценарии!D7*1000000*Допущения!C7,MAX(0,MAX(0,Допущения!C5-Сценарии!D7*1000000*Допущения!C7)-IF(MAX(0,Допущения!C5-Сценарии!D7*1000000*Допущения!C7)=0,Сценарии!D7*1000000*Допущения!C6,IF(MAX(0,Допущения!C5-Сценарии!D7*1000000*Допущения!C7)>=Сценарии!D7*1000000*Допущения!C7,Сценарии!D7*1000000*Допущения!C7,MAX(0,Допущения!C5-Сценарии!D7*1000000*Допущения!C7)+(Сценарии!D7*1000000-MAX(0,Допущения!C5-Сценарии!D7*1000000*Допущения!C7)/Допущения!C7)*Допущения!C6)))+(Сценарии!D7*1000000-MAX(0,MAX(0,Допущения!C5-Сценарии!D7*1000000*Допущения!C7)-IF(MAX(0,Допущения!C5-Сценарии!D7*1000000*Допущения!C7)=0,Сценарии!D7*1000000*Допущения!C6,IF(MAX(0,Допущения!C5-Сценарии!D7*1000000*Допущения!C7)>=Сценарии!D7*1000000*Допущения!C7,Сценарии!D7*1000000*Допущения!C7,MAX(0,Допущения!C5-Сценарии!D7*1000000*Допущения!C7)+(Сценарии!D7*1000000-MAX(0,Допущения!C5-Сценарии!D7*1000000*Допущения!C7)/Допущения!C7)*Допущения!C6)))/Допущения!C7)*Допущения!C6))*(C5/Допущения!C5))/C5 -> 0.48925758 | E27: =(IF(MAX(0,MAX(0,Допущения!C5-Сценарии!E7*1000000*Допущения!C7)-IF(MAX(0,Допущения!C5-Сценарии!E7*1000000*Допущения!C7)=0,Сценарии!E7*1000000*Допущения!C6,IF(MAX(0,Допущения!C5-Сценарии!E7*1000000*Допущения!C7)>=Сценарии!E7*1000000*Допущения!C7,Сценарии!E7*1000000*Допущения!C7,MAX(0,Допущения!C5-Сценарии!E7*1000000*Допущения!C7)+(Сценарии!E7*1000000-MAX(0,Допущения!C5-Сценарии!E7*1000000*Допущения!C7)/Допущения!C7)*Допущения!C6)))=0,Сценарии!E7*1000000*Допущения!C6,IF(MAX(0,MAX(0,Допущения!C5-Сценарии!E7*1000000*Допущения!C7)-IF(MAX(0,Допущения!C5-Сценарии!E7*1000000*Допущения!C7)=0,Сценарии!E7*1000000*Допущения!C6,IF(MAX(0,Допущения!C5-Сценарии!E7*1000000*Допущения!C7)>=Сценарии!E7*1000000*Допущения!C7,Сценарии!E7*1000000*Допущения!C7,MAX(0,Допущения!C5-Сценарии!E7*1000000*Допущения!C7)+(Сценарии!E7*1000000-MAX(0,Допущения!C5-Сценарии!E7*1000000*Допущения!C7)/Допущения!C7)*Допущения!C6)))>=Сценарии!E7*1000000*Допущения!C7,Сценарии!E7*1000000*Допущения!C7,MAX(0,MAX(0,Допущения!C5-Сценарии!E7*1000000*Допущения!C7)-IF(MAX(0,Допущения!C5-Сценарии!E7*1000000*Допущения!C7)=0,Сценарии!E7*1000000*Допущения!C6,IF(MAX(0,Допущения!C5-Сценарии!E7*1000000*Допущения!C7)>=Сценарии!E7*1000000*Допущения!C7,Сценарии!E7*1000000*Допущения!C7,MAX(0,Допущения!C5-Сценарии!E7*1000000*Допущения!C7)+(Сценарии!E7*1000000-MAX(0,Допущения!C5-Сценарии!E7*1000000*Допущения!C7)/Допущения!C7)*Допущения!C6)))+(Сценарии!E7*1000000-MAX(0,MAX(0,Допущения!C5-Сценарии!E7*1000000*Допущения!C7)-IF(MAX(0,Допущения!C5-Сценарии!E7*1000000*Допущения!C7)=0,Сценарии!E7*1000000*Допущения!C6,IF(MAX(0,Допущения!C5-Сценарии!E7*1000000*Допущения!C7)>=Сценарии!E7*1000000*Допущения!C7,Сценарии!E7*1000000*Допущения!C7,MAX(0,Допущения!C5-Сценарии!E7*1000000*Допущения!C7)+(Сценарии!E7*1000000-MAX(0,Допущения!C5-Сценарии!E7*1000000*Допущения!C7)/Допущения!C7)*Допущения!C6)))/Допущения!C7)*Допущения!C6))*(C5/Допущения!C5))/C5 -> 0.58710909
B29: ИТОГО ДИВИДЕНДОВ 2027–2029 | C29: =Сценарии!C7*1000000*Допущения!C7*(C5/Допущения!C5)+IF(MAX(0,Допущения!C5-Сценарии!C7*1000000*Допущения!C7)=0,Сценарии!C7*1000000*Допущения!C6,IF(MAX(0,Допущения!C5-Сценарии!C7*1000000*Допущения!C7)>=Сценарии!C7*1000000*Допущения!C7,Сценарии!C7*1000000*Допущения!C7,MAX(0,Допущения!C5-Сценарии!C7*1000000*Допущения!C7)+(Сценарии!C7*1000000-MAX(0,Допущения!C5-Сценарии!C7*1000000*Допущения!C7)/Допущения!C7)*Допущения!C6))*(C5/Допущения!C5)+IF(MAX(0,MAX(0,Допущения!C5-Сценарии!C7*1000000*Допущения!C7)-IF(MAX(0,Допущения!C5-Сценарии!C7*1000000*Допущения!C7)=0,Сценарии!C7*1000000*Допущения!C6,IF(MAX(0,Допущения!C5-Сценарии!C7*1000000*Допущения!C7)>=Сценарии!C7*1000000*Допущения!C7,Сценарии!C7*1000000*Допущения!C7,MAX(0,Допущения!C5-Сценарии!C7*1000000*Допущения!C7)+(Сценарии!C7*1000000-MAX(0,Допущения!C5-Сценарии!C7*1000000*Допущения!C7)/Допущения!C7)*Допущения!C6)))=0,Сценарии!C7*1000000*Допущения!C6,IF(MAX(0,MAX(0,Допущения!C5-Сценарии!C7*1000000*Допущения!C7)-IF(MAX(0,Допущения!C5-Сценарии!C7*1000000*Допущения!C7)=0,Сценарии!C7*1000000*Допущения!C6,IF(MAX(0,Допущения!C5-Сценарии!C7*1000000*Допущения!C7)>=Сценарии!C7*1000000*Допущения!C7,Сценарии!C7*1000000*Допущения!C7,MAX(0,Допущения!C5-Сценарии!C7*1000000*Допущения!C7)+(Сценарии!C7*1000000-MAX(0,Допущения!C5-Сценарии!C7*1000000*Допущения!C7)/Допущения!C7)*Допущения!C6)))>=Сценарии!C7*1000000*Допущения!C7,Сценарии!C7*1000000*Допущения!C7,MAX(0,MAX(0,Допущения!C5-Сценарии!C7*1000000*Допущения!C7)-IF(MAX(0,Допущения!C5-Сценарии!C7*1000000*Допущения!C7)=0,Сценарии!C7*1000000*Допущения!C6,IF(MAX(0,Допущения!C5-Сценарии!C7*1000000*Допущения!C7)>=Сценарии!C7*1000000*Допущения!C7,Сценарии!C7*1000000*Допущения!C7,MAX(0,Допущения!C5-Сценарии!C7*1000000*Допущения!C7)+(Сценарии!C7*1000000-MAX(0,Допущения!C5-Сценарии!C7*1000000*Допущения!C7)/Допущения!C7)*Допущения!C6)))+(Сценарии!C7*1000000-MAX(0,MAX(0,Допущения!C5-Сценарии!C7*1000000*Допущения!C7)-IF(MAX(0,Допущения!C5-Сценарии!C7*1000000*Допущения!C7)=0,Сценарии!C7*1000000*Допущения!C6,IF(MAX(0,Допущения!C5-Сценарии!C7*1000000*Допущения!C7)>=Сценарии!C7*1000000*Допущения!C7,Сценарии!C7*1000000*Допущения!C7,MAX(0,Допущения!C5-Сценарии!C7*1000000*Допущения!C7)+(Сценарии!C7*1000000-MAX(0,Допущения!C5-Сценарии!C7*1000000*Допущения!C7)/Допущения!C7)*Допущения!C6)))/Допущения!C7)*Допущения!C6))*(C5/Допущения!C5) -> 1561718.2 | D29: =Сценарии!D7*1000000*Допущения!C7*(C5/Допущения!C5)+IF(MAX(0,Допущения!C5-Сценарии!D7*1000000*Допущения!C7)=0,Сценарии!D7*1000000*Допущения!C6,IF(MAX(0,Допущения!C5-Сценарии!D7*1000000*Допущения!C7)>=Сценарии!D7*1000000*Допущения!C7,Сценарии!D7*1000000*Допущения!C7,MAX(0,Допущения!C5-Сценарии!D7*1000000*Допущения!C7)+(Сценарии!D7*1000000-MAX(0,Допущения!C5-Сценарии!D7*1000000*Допущения!C7)/Допущения!C7)*Допущения!C6))*(C5/Допущения!C5)+IF(MAX(0,MAX(0,Допущения!C5-Сценарии!D7*1000000*Допущения!C7)-IF(MAX(0,Допущения!C5-Сценарии!D7*1000000*Допущения!C7)=0,Сценарии!D7*1000000*Допущения!C6,IF(MAX(0,Допущения!C5-Сценарии!D7*1000000*Допущения!C7)>=Сценарии!D7*1000000*Допущения!C7,Сценарии!D7*1000000*Допущения!C7,MAX(0,Допущения!C5-Сценарии!D7*1000000*Допущения!C7)+(Сценарии!D7*1000000-MAX(0,Допущения!C5-Сценарии!D7*1000000*Допущения!C7)/Допущения!C7)*Допущения!C6)))=0,Сценарии!D7*1000000*Допущения!C6,IF(MAX(0,MAX(0,Допущения!C5-Сценарии!D7*1000000*Допущения!C7)-IF(MAX(0,Допущения!C5-Сценарии!D7*1000000*Допущения!C7)=0,Сценарии!D7*1000000*Допущения!C6,IF(MAX(0,Допущения!C5-Сценарии!D7*1000000*Допущения!C7)>=Сценарии!D7*1000000*Допущения!C7,Сценарии!D7*1000000*Допущения!C7,MAX(0,Допущения!C5-Сценарии!D7*1000000*Допущения!C7)+(Сценарии!D7*1000000-MAX(0,Допущения!C5-Сценарии!D7*1000000*Допущения!C7)/Допущения!C7)*Допущения!C6)))>=Сценарии!D7*1000000*Допущения!C7,Сценарии!D7*1000000*Допущения!C7,MAX(0,MAX(0,Допущения!C5-Сценарии!D7*1000000*Допущения!C7)-IF(MAX(0,Допущения!C5-Сценарии!D7*1000000*Допущения!C7)=0,Сценарии!D7*1000000*Допущения!C6,IF(MAX(0,Допущения!C5-Сценарии!D7*1000000*Допущения!C7)>=Сценарии!D7*1000000*Допущения!C7,Сценарии!D7*1000000*Допущения!C7,MAX(0,Допущения!C5-Сценарии!D7*1000000*Допущения!C7)+(Сценарии!D7*1000000-MAX(0,Допущения!C5-Сценарии!D7*1000000*Допущения!C7)/Допущения!C7)*Допущения!C6)))+(Сценарии!D7*1000000-MAX(0,MAX(0,Допущения!C5-Сценарии!D7*1000000*Допущения!C7)-IF(MAX(0,Допущения!C5-Сценарии!D7*1000000*Допущения!C7)=0,Сценарии!D7*1000000*Допущения!C6,IF(MAX(0,Допущения!C5-Сценарии!D7*1000000*Допущения!C7)>=Сценарии!D7*1000000*Допущения!C7,Сценарии!D7*1000000*Допущения!C7,MAX(0,Допущения!C5-Сценарии!D7*1000000*Допущения!C7)+(Сценарии!D7*1000000-MAX(0,Допущения!C5-Сценарии!D7*1000000*Допущения!C7)/Допущения!C7)*Допущения!C6)))/Допущения!C7)*Допущения!C6))*(C5/Допущения!C5) -> 1855272.7 | E29: =Сценарии!E7*1000000*Допущения!C7*(C5/Допущения!C5)+IF(MAX(0,Допущения!C5-Сценарии!E7*1000000*Допущения!C7)=0,Сценарии!E7*1000000*Допущения!C6,IF(MAX(0,Допущения!C5-Сценарии!E7*1000000*Допущения!C7)>=Сценарии!E7*1000000*Допущения!C7,Сценарии!E7*1000000*Допущения!C7,MAX(0,Допущения!C5-Сценарии!E7*1000000*Допущения!C7)+(Сценарии!E7*1000000-MAX(0,Допущения!C5-Сценарии!E7*1000000*Допущения!C7)/Допущения!C7)*Допущения!C6))*(C5/Допущения!C5)+IF(MAX(0,MAX(0,Допущения!C5-Сценарии!E7*1000000*Допущения!C7)-IF(MAX(0,Допущения!C5-Сценарии!E7*1000000*Допущения!C7)=0,Сценарии!E7*1000000*Допущения!C6,IF(MAX(0,Допущения!C5-Сценарии!E7*1000000*Допущения!C7)>=Сценарии!E7*1000000*Допущения!C7,Сценарии!E7*1000000*Допущения!C7,MAX(0,Допущения!C5-Сценарии!E7*1000000*Допущения!C7)+(Сценарии!E7*1000000-MAX(0,Допущения!C5-Сценарии!E7*1000000*Допущения!C7)/Допущения!C7)*Допущения!C6)))=0,Сценарии!E7*1000000*Допущения!C6,IF(MAX(0,MAX(0,Допущения!C5-Сценарии!E7*1000000*Допущения!C7)-IF(MAX(0,Допущения!C5-Сценарии!E7*1000000*Допущения!C7)=0,Сценарии!E7*1000000*Допущения!C6,IF(MAX(0,Допущения!C5-Сценарии!E7*1000000*Допущения!C7)>=Сценарии!E7*1000000*Допущения!C7,Сценарии!E7*1000000*Допущения!C7,MAX(0,Допущения!C5-Сценарии!E7*1000000*Допущения!C7)+(Сценарии!E7*1000000-MAX(0,Допущения!C5-Сценарии!E7*1000000*Допущения!C7)/Допущения!C7)*Допущения!C6)))>=Сценарии!E7*1000000*Допущения!C7,Сценарии!E7*1000000*Допущения!C7,MAX(0,MAX(0,Допущения!C5-Сценарии!E7*1000000*Допущения!C7)-IF(MAX(0,Допущения!C5-Сценарии!E7*1000000*Допущения!C7)=0,Сценарии!E7*1000000*Допущения!C6,IF(MAX(0,Допущения!C5-Сценарии!E7*1000000*Допущения!C7)>=Сценарии!E7*1000000*Допущения!C7,Сценарии!E7*1000000*Допущения!C7,MAX(0,Допущения!C5-Сценарии!E7*1000000*Допущения!C7)+(Сценарии!E7*1000000-MAX(0,Допущения!C5-Сценарии!E7*1000000*Допущения!C7)/Допущения!C7)*Допущения!C6)))+(Сценарии!E7*1000000-MAX(0,MAX(0,Допущения!C5-Сценарии!E7*1000000*Допущения!C7)-IF(MAX(0,Допущения!C5-Сценарии!E7*1000000*Допущения!C7)=0,Сценарии!E7*1000000*Допущения!C6,IF(MAX(0,Допущения!C5-Сценарии!E7*1000000*Допущения!C7)>=Сценарии!E7*1000000*Допущения!C7,Сценарии!E7*1000000*Допущения!C7,MAX(0,Допущения!C5-Сценарии!E7*1000000*Допущения!C7)+(Сценарии!E7*1000000-MAX(0,Допущения!C5-Сценарии!E7*1000000*Допущения!C7)/Допущения!C7)*Допущения!C6)))/Допущения!C7)*Допущения!C6))*(C5/Допущения!C5) -> 2148827.3
B31: СТОИМОСТЬ ВАШЕЙ ДОЛИ ПРИ ПРОДАЖЕ (оценка: прибыль × 3×)
B33: Годовая прибыль проекта (1 сезон) | C33: =Сценарии!C7 -> 52.72 | D33: =Сценарии!D7 -> 65.9 | E33: =Сценарии!E7 -> 79.08
B34: Оценка компании (прибыль × 3×) | C34: =Сценарии!C12 -> 158.16 | D34: =Сценарии!D12 -> 197.7 | E34: =Сценарии!E12 -> 237.24
B35: Стоимость доли всех инвесторов (49%) | C35: =Сценарии!C13 -> 77.4984 | D35: =Сценарии!D13 -> 96.873 | E35: =Сценарии!E13 -> 116.2476
B36: 📈 Стоимость ВАШИХ акций при продаже | C36: =Сценарии!C13*1000000*(C5/Допущения!C5) -> 1174218.2 | D36: =Сценарии!D13*1000000*(C5/Допущения!C5) -> 1467772.7 | E36: =Сценарии!E13*1000000*(C5/Допущения!C5) -> 1761327.3
B37: Прирост стоимости (сверх вложений) | C37: =Сценарии!C13*1000000*(C5/Допущения!C5)-C5 -> 174218.18 | D37: =Сценарии!D13*1000000*(C5/Допущения!C5)-C5 -> 467772.73 | E37: =Сценарии!E13*1000000*(C5/Допущения!C5)-C5 -> 761327.27
B39: ИТОГОВЫЙ РАСЧЁТ — СУММАРНЫЙ ДОХОД ЗА 3 ГОДА
B41: Дивиденды за 2027–2029 годы | C41: =Сценарии!C7*1000000*Допущения!C7*(C5/Допущения!C5)+IF(MAX(0,Допущения!C5-Сценарии!C7*1000000*Допущения!C7)=0,Сценарии!C7*1000000*Допущения!C6,IF(MAX(0,Допущения!C5-Сценарии!C7*1000000*Допущения!C7)>=Сценарии!C7*1000000*Допущения!C7,Сценарии!C7*1000000*Допущения!C7,MAX(0,Допущения!C5-Сценарии!C7*1000000*Допущения!C7)+(Сценарии!C7*1000000-MAX(0,Допущения!C5-Сценарии!C7*1000000*Допущения!C7)/Допущения!C7)*Допущения!C6))*(C5/Допущения!C5)+IF(MAX(0,MAX(0,Допущения!C5-Сценарии!C7*1000000*Допущения!C7)-IF(MAX(0,Допущения!C5-Сценарии!C7*1000000*Допущения!C7)=0,Сценарии!C7*1000000*Допущения!C6,IF(MAX(0,Допущения!C5-Сценарии!C7*1000000*Допущения!C7)>=Сценарии!C7*1000000*Допущения!C7,Сценарии!C7*1000000*Допущения!C7,MAX(0,Допущения!C5-Сценарии!C7*1000000*Допущения!C7)+(Сценарии!C7*1000000-MAX(0,Допущения!C5-Сценарии!C7*1000000*Допущения!C7)/Допущения!C7)*Допущения!C6)))=0,Сценарии!C7*1000000*Допущения!C6,IF(MAX(0,MAX(0,Допущения!C5-Сценарии!C7*1000000*Допущения!C7)-IF(MAX(0,Допущения!C5-Сценарии!C7*1000000*Допущения!C7)=0,Сценарии!C7*1000000*Допущения!C6,IF(MAX(0,Допущения!C5-Сценарии!C7*1000000*Допущения!C7)>=Сценарии!C7*1000000*Допущения!C7,Сценарии!C7*1000000*Допущения!C7,MAX(0,Допущения!C5-Сценарии!C7*1000000*Допущения!C7)+(Сценарии!C7*1000000-MAX(0,Допущения!C5-Сценарии!C7*1000000*Допущения!C7)/Допущения!C7)*Допущения!C6)))>=Сценарии!C7*1000000*Допущения!C7,Сценарии!C7*1000000*Допущения!C7,MAX(0,MAX(0,Допущения!C5-Сценарии!C7*1000000*Допущения!C7)-IF(MAX(0,Допущения!C5-Сценарии!C7*1000000*Допущения!C7)=0,Сценарии!C7*1000000*Допущения!C6,IF(MAX(0,Допущения!C5-Сценарии!C7*1000000*Допущения!C7)>=Сценарии!C7*1000000*Допущения!C7,Сценарии!C7*1000000*Допущения!C7,MAX(0,Допущения!C5-Сценарии!C7*1000000*Допущения!C7)+(Сценарии!C7*1000000-MAX(0,Допущения!C5-Сценарии!C7*1000000*Допущения!C7)/Допущения!C7)*Допущения!C6)))+(Сценарии!C7*1000000-MAX(0,MAX(0,Допущения!C5-Сценарии!C7*1000000*Допущения!C7)-IF(MAX(0,Допущения!C5-Сценарии!C7*1000000*Допущения!C7)=0,Сценарии!C7*1000000*Допущения!C6,IF(MAX(0,Допущения!C5-Сценарии!C7*1000000*Допущения!C7)>=Сценарии!C7*1000000*Допущения!C7,Сценарии!C7*1000000*Допущения!C7,MAX(0,Допущения!C5-Сценарии!C7*1000000*Допущения!C7)+(Сценарии!C7*1000000-MAX(0,Допущения!C5-Сценарии!C7*1000000*Допущения!C7)/Допущения!C7)*Допущения!C6)))/Допущения!C7)*Допущения!C6))*(C5/Допущения!C5) -> 1561718.2 | D41: =Сценарии!D7*1000000*Допущения!C7*(C5/Допущения!C5)+IF(MAX(0,Допущения!C5-Сценарии!D7*1000000*Допущения!C7)=0,Сценарии!D7*1000000*Допущения!C6,IF(MAX(0,Допущения!C5-Сценарии!D7*1000000*Допущения!C7)>=Сценарии!D7*1000000*Допущения!C7,Сценарии!D7*1000000*Допущения!C7,MAX(0,Допущения!C5-Сценарии!D7*1000000*Допущения!C7)+(Сценарии!D7*1000000-MAX(0,Допущения!C5-Сценарии!D7*1000000*Допущения!C7)/Допущения!C7)*Допущения!C6))*(C5/Допущения!C5)+IF(MAX(0,MAX(0,Допущения!C5-Сценарии!D7*1000000*Допущения!C7)-IF(MAX(0,Допущения!C5-Сценарии!D7*1000000*Допущения!C7)=0,Сценарии!D7*1000000*Допущения!C6,IF(MAX(0,Допущения!C5-Сценарии!D7*1000000*Допущения!C7)>=Сценарии!D7*1000000*Допущения!C7,Сценарии!D7*1000000*Допущения!C7,MAX(0,Допущения!C5-Сценарии!D7*1000000*Допущения!C7)+(Сценарии!D7*1000000-MAX(0,Допущения!C5-Сценарии!D7*1000000*Допущения!C7)/Допущения!C7)*Допущения!C6)))=0,Сценарии!D7*1000000*Допущения!C6,IF(MAX(0,MAX(0,Допущения!C5-Сценарии!D7*1000000*Допущения!C7)-IF(MAX(0,Допущения!C5-Сценарии!D7*1000000*Допущения!C7)=0,Сценарии!D7*1000000*Допущения!C6,IF(MAX(0,Допущения!C5-Сценарии!D7*1000000*Допущения!C7)>=Сценарии!D7*1000000*Допущения!C7,Сценарии!D7*1000000*Допущения!C7,MAX(0,Допущения!C5-Сценарии!D7*1000000*Допущения!C7)+(Сценарии!D7*1000000-MAX(0,Допущения!C5-Сценарии!D7*1000000*Допущения!C7)/Допущения!C7)*Допущения!C6)))>=Сценарии!D7*1000000*Допущения!C7,Сценарии!D7*1000000*Допущения!C7,MAX(0,MAX(0,Допущения!C5-Сценарии!D7*1000000*Допущения!C7)-IF(MAX(0,Допущения!C5-Сценарии!D7*1000000*Допущения!C7)=0,Сценарии!D7*1000000*Допущения!C6,IF(MAX(0,Допущения!C5-Сценарии!D7*1000000*Допущения!C7)>=Сценарии!D7*1000000*Допущения!C7,Сценарии!D7*1000000*Допущения!C7,MAX(0,Допущения!C5-Сценарии!D7*1000000*Допущения!C7)+(Сценарии!D7*1000000-MAX(0,Допущения!C5-Сценарии!D7*1000000*Допущения!C7)/Допущения!C7)*Допущения!C6)))+(Сценарии!D7*1000000-MAX(0,MAX(0,Допущения!C5-Сценарии!D7*1000000*Допущения!C7)-IF(MAX(0,Допущения!C5-Сценарии!D7*1000000*Допущения!C7)=0,Сценарии!D7*1000000*Допущения!C6,IF(MAX(0,Допущения!C5-Сценарии!D7*1000000*Допущения!C7)>=Сценарии!D7*1000000*Допущения!C7,Сценарии!D7*1000000*Допущения!C7,MAX(0,Допущения!C5-Сценарии!D7*1000000*Допущения!C7)+(Сценарии!D7*1000000-MAX(0,Допущения!C5-Сценарии!D7*1000000*Допущения!C7)/Допущения!C7)*Допущения!C6)))/Допущения!C7)*Допущения!C6))*(C5/Допущения!C5) -> 1855272.7 | E41: =Сценарии!E7*1000000*Допущения!C7*(C5/Допущения!C5)+IF(MAX(0,Допущения!C5-Сценарии!E7*1000000*Допущения!C7)=0,Сценарии!E7*1000000*Допущения!C6,IF(MAX(0,Допущения!C5-Сценарии!E7*1000000*Допущения!C7)>=Сценарии!E7*1000000*Допущения!C7,Сценарии!E7*1000000*Допущения!C7,MAX(0,Допущения!C5-Сценарии!E7*1000000*Допущения!C7)+(Сценарии!E7*1000000-MAX(0,Допущения!C5-Сценарии!E7*1000000*Допущения!C7)/Допущения!C7)*Допущения!C6))*(C5/Допущения!C5)+IF(MAX(0,MAX(0,Допущения!C5-Сценарии!E7*1000000*Допущения!C7)-IF(MAX(0,Допущения!C5-Сценарии!E7*1000000*Допущения!C7)=0,Сценарии!E7*1000000*Допущения!C6,IF(MAX(0,Допущения!C5-Сценарии!E7*1000000*Допущения!C7)>=Сценарии!E7*1000000*Допущения!C7,Сценарии!E7*1000000*Допущения!C7,MAX(0,Допущения!C5-Сценарии!E7*1000000*Допущения!C7)+(Сценарии!E7*1000000-MAX(0,Допущения!C5-Сценарии!E7*1000000*Допущения!C7)/Допущения!C7)*Допущения!C6)))=0,Сценарии!E7*1000000*Допущения!C6,IF(MAX(0,MAX(0,Допущения!C5-Сценарии!E7*1000000*Допущения!C7)-IF(MAX(0,Допущения!C5-Сценарии!E7*1000000*Допущения!C7)=0,Сценарии!E7*1000000*Допущения!C6,IF(MAX(0,Допущения!C5-Сценарии!E7*1000000*Допущения!C7)>=Сценарии!E7*1000000*Допущения!C7,Сценарии!E7*1000000*Допущения!C7,MAX(0,Допущения!C5-Сценарии!E7*1000000*Допущения!C7)+(Сценарии!E7*1000000-MAX(0,Допущения!C5-Сценарии!E7*1000000*Допущения!C7)/Допущения!C7)*Допущения!C6)))>=Сценарии!E7*1000000*Допущения!C7,Сценарии!E7*1000000*Допущения!C7,MAX(0,MAX(0,Допущения!C5-Сценарии!E7*1000000*Допущения!C7)-IF(MAX(0,Допущения!C5-Сценарии!E7*1000000*Допущения!C7)=0,Сценарии!E7*1000000*Допущения!C6,IF(MAX(0,Допущения!C5-Сценарии!E7*1000000*Допущения!C7)>=Сценарии!E7*1000000*Допущения!C7,Сценарии!E7*1000000*Допущения!C7,MAX(0,Допущения!C5-Сценарии!E7*1000000*Допущения!C7)+(Сценарии!E7*1000000-MAX(0,Допущения!C5-Сценарии!E7*1000000*Допущения!C7)/Допущения!C7)*Допущения!C6)))+(Сценарии!E7*1000000-MAX(0,MAX(0,Допущения!C5-Сценарии!E7*1000000*Допущения!C7)-IF(MAX(0,Допущения!C5-Сценарии!E7*1000000*Допущения!C7)=0,Сценарии!E7*1000000*Допущения!C6,IF(MAX(0,Допущения!C5-Сценарии!E7*1000000*Допущения!C7)>=Сценарии!E7*1000000*Допущения!C7,Сценарии!E7*1000000*Допущения!C7,MAX(0,Допущения!C5-Сценарии!E7*1000000*Допущения!C7)+(Сценарии!E7*1000000-MAX(0,Допущения!C5-Сценарии!E7*1000000*Допущения!C7)/Допущения!C7)*Допущения!C6)))/Допущения!C7)*Допущения!C6))*(C5/Допущения!C5) -> 2148827.3
B42: Стоимость ваших акций (продажа) | C42: =Сценарии!C13*1000000*(C5/Допущения!C5) -> 1174218.2 | D42: =Сценарии!D13*1000000*(C5/Допущения!C5) -> 1467772.7 | E42: =Сценарии!E13*1000000*(C5/Допущения!C5) -> 1761327.3
B43: 🏆 TOTAL RETURN — суммарный доход | C43: =(Сценарии!C7*1000000*Допущения!C7+IF(MAX(0,Допущения!C5-Сценарии!C7*1000000*Допущения!C7)=0,Сценарии!C7*1000000*Допущения!C6,IF(MAX(0,Допущения!C5-Сценарии!C7*1000000*Допущения!C7)>=Сценарии!C7*1000000*Допущения!C7,Сценарии!C7*1000000*Допущения!C7,MAX(0,Допущения!C5-Сценарии!C7*1000000*Допущения!C7)+(Сценарии!C7*1000000-MAX(0,Допущения!C5-Сценарии!C7*1000000*Допущения!C7)/Допущения!C7)*Допущения!C6))+IF(MAX(0,MAX(0,Допущения!C5-Сценарии!C7*1000000*Допущения!C7)-IF(MAX(0,Допущения!C5-Сценарии!C7*1000000*Допущения!C7)=0,Сценарии!C7*1000000*Допущения!C6,IF(MAX(0,Допущения!C5-Сценарии!C7*1000000*Допущения!C7)>=Сценарии!C7*1000000*Допущения!C7,Сценарии!C7*1000000*Допущения!C7,MAX(0,Допущения!C5-Сценарии!C7*1000000*Допущения!C7)+(Сценарии!C7*1000000-MAX(0,Допущения!C5-Сценарии!C7*1000000*Допущения!C7)/Допущения!C7)*Допущения!C6)))=0,Сценарии!C7*1000000*Допущения!C6,IF(MAX(0,MAX(0,Допущения!C5-Сценарии!C7*1000000*Допущения!C7)-IF(MAX(0,Допущения!C5-Сценарии!C7*1000000*Допущения!C7)=0,Сценарии!C7*1000000*Допущения!C6,IF(MAX(0,Допущения!C5-Сценарии!C7*1000000*Допущения!C7)>=Сценарии!C7*1000000*Допущения!C7,Сценарии!C7*1000000*Допущения!C7,MAX(0,Допущения!C5-Сценарии!C7*1000000*Допущения!C7)+(Сценарии!C7*1000000-MAX(0,Допущения!C5-Сценарии!C7*1000000*Допущения!C7)/Допущения!C7)*Допущения!C6)))>=Сценарии!C7*1000000*Допущения!C7,Сценарии!C7*1000000*Допущения!C7,MAX(0,MAX(0,Допущения!C5-Сценарии!C7*1000000*Допущения!C7)-IF(MAX(0,Допущения!C5-Сценарии!C7*1000000*Допущения!C7)=0,Сценарии!C7*1000000*Допущения!C6,IF(MAX(0,Допущения!C5-Сценарии!C7*1000000*Допущения!C7)>=Сценарии!C7*1000000*Допущения!C7,Сценарии!C7*1000000*Допущения!C7,MAX(0,Допущения!C5-Сценарии!C7*1000000*Допущения!C7)+(Сценарии!C7*1000000-MAX(0,Допущения!C5-Сценарии!C7*1000000*Допущения!C7)/Допущения!C7)*Допущения!C6)))+(Сценарии!C7*1000000-MAX(0,MAX(0,Допущения!C5-Сценарии!C7*1000000*Допущения!C7)-IF(MAX(0,Допущения!C5-Сценарии!C7*1000000*Допущения!C7)=0,Сценарии!C7*1000000*Допущения!C6,IF(MAX(0,Допущения!C5-Сценарии!C7*1000000*Допущения!C7)>=Сценарии!C7*1000000*Допущения!C7,Сценарии!C7*1000000*Допущения!C7,MAX(0,Допущения!C5-Сценарии!C7*1000000*Допущения!C7)+(Сценарии!C7*1000000-MAX(0,Допущения!C5-Сценарии!C7*1000000*Допущения!C7)/Допущения!C7)*Допущения!C6)))/Допущения!C7)*Допущения!C6)))*(C5/Допущения!C5)+Сценарии!C13*1000000*(C5/Допущения!C5) -> 2735936.4 | D43: =(Сценарии!D7*1000000*Допущения!C7+IF(MAX(0,Допущения!C5-Сценарии!D7*1000000*Допущения!C7)=0,Сценарии!D7*1000000*Допущения!C6,IF(MAX(0,Допущения!C5-Сценарии!D7*1000000*Допущения!C7)>=Сценарии!D7*1000000*Допущения!C7,Сценарии!D7*1000000*Допущения!C7,MAX(0,Допущения!C5-Сценарии!D7*1000000*Допущения!C7)+(Сценарии!D7*1000000-MAX(0,Допущения!C5-Сценарии!D7*1000000*Допущения!C7)/Допущения!C7)*Допущения!C6))+IF(MAX(0,MAX(0,Допущения!C5-Сценарии!D7*1000000*Допущения!C7)-IF(MAX(0,Допущения!C5-Сценарии!D7*1000000*Допущения!C7)=0,Сценарии!D7*1000000*Допущения!C6,IF(MAX(0,Допущения!C5-Сценарии!D7*1000000*Допущения!C7)>=Сценарии!D7*1000000*Допущения!C7,Сценарии!D7*1000000*Допущения!C7,MAX(0,Допущения!C5-Сценарии!D7*1000000*Допущения!C7)+(Сценарии!D7*1000000-MAX(0,Допущения!C5-Сценарии!D7*1000000*Допущения!C7)/Допущения!C7)*Допущения!C6)))=0,Сценарии!D7*1000000*Допущения!C6,IF(MAX(0,MAX(0,Допущения!C5-Сценарии!D7*1000000*Допущения!C7)-IF(MAX(0,Допущения!C5-Сценарии!D7*1000000*Допущения!C7)=0,Сценарии!D7*1000000*Допущения!C6,IF(MAX(0,Допущения!C5-Сценарии!D7*1000000*Допущения!C7)>=Сценарии!D7*1000000*Допущения!C7,Сценарии!D7*1000000*Допущения!C7,MAX(0,Допущения!C5-Сценарии!D7*1000000*Допущения!C7)+(Сценарии!D7*1000000-MAX(0,Допущения!C5-Сценарии!D7*1000000*Допущения!C7)/Допущения!C7)*Допущения!C6)))>=Сценарии!D7*1000000*Допущения!C7,Сценарии!D7*1000000*Допущения!C7,MAX(0,MAX(0,Допущения!C5-Сценарии!D7*1000000*Допущения!C7)-IF(MAX(0,Допущения!C5-Сценарии!D7*1000000*Допущения!C7)=0,Сценарии!D7*1000000*Допущения!C6,IF(MAX(0,Допущения!C5-Сценарии!D7*1000000*Допущения!C7)>=Сценарии!D7*1000000*Допущения!C7,Сценарии!D7*1000000*Допущения!C7,MAX(0,Допущения!C5-Сценарии!D7*1000000*Допущения!C7)+(Сценарии!D7*1000000-MAX(0,Допущения!C5-Сценарии!D7*1000000*Допущения!C7)/Допущения!C7)*Допущения!C6)))+(Сценарии!D7*1000000-MAX(0,MAX(0,Допущения!C5-Сценарии!D7*1000000*Допущения!C7)-IF(MAX(0,Допущения!C5-Сценарии!D7*1000000*Допущения!C7)=0,Сценарии!D7*1000000*Допущения!C6,IF(MAX(0,Допущения!C5-Сценарии!D7*1000000*Допущения!C7)>=Сценарии!D7*1000000*Допущения!C7,Сценарии!D7*1000000*Допущения!C7,MAX(0,Допущения!C5-Сценарии!D7*1000000*Допущения!C7)+(Сценарии!D7*1000000-MAX(0,Допущения!C5-Сценарии!D7*1000000*Допущения!C7)/Допущения!C7)*Допущения!C6)))/Допущения!C7)*Допущения!C6)))*(C5/Допущения!C5)+Сценарии!D13*1000000*(C5/Допущения!C5) -> 3323045.5 | E43: =(Сценарии!E7*1000000*Допущения!C7+IF(MAX(0,Допущения!C5-Сценарии!E7*1000000*Допущения!C7)=0,Сценарии!E7*1000000*Допущения!C6,IF(MAX(0,Допущения!C5-Сценарии!E7*1000000*Допущения!C7)>=Сценарии!E7*1000000*Допущения!C7,Сценарии!E7*1000000*Допущения!C7,MAX(0,Допущения!C5-Сценарии!E7*1000000*Допущения!C7)+(Сценарии!E7*1000000-MAX(0,Допущения!C5-Сценарии!E7*1000000*Допущения!C7)/Допущения!C7)*Допущения!C6))+IF(MAX(0,MAX(0,Допущения!C5-Сценарии!E7*1000000*Допущения!C7)-IF(MAX(0,Допущения!C5-Сценарии!E7*1000000*Допущения!C7)=0,Сценарии!E7*1000000*Допущения!C6,IF(MAX(0,Допущения!C5-Сценарии!E7*1000000*Допущения!C7)>=Сценарии!E7*1000000*Допущения!C7,Сценарии!E7*1000000*Допущения!C7,MAX(0,Допущения!C5-Сценарии!E7*1000000*Допущения!C7)+(Сценарии!E7*1000000-MAX(0,Допущения!C5-Сценарии!E7*1000000*Допущения!C7)/Допущения!C7)*Допущения!C6)))=0,Сценарии!E7*1000000*Допущения!C6,IF(MAX(0,MAX(0,Допущения!C5-Сценарии!E7*1000000*Допущения!C7)-IF(MAX(0,Допущения!C5-Сценарии!E7*1000000*Допущения!C7)=0,Сценарии!E7*1000000*Допущения!C6,IF(MAX(0,Допущения!C5-Сценарии!E7*1000000*Допущения!C7)>=Сценарии!E7*1000000*Допущения!C7,Сценарии!E7*1000000*Допущения!C7,MAX(0,Допущения!C5-Сценарии!E7*1000000*Допущения!C7)+(Сценарии!E7*1000000-MAX(0,Допущения!C5-Сценарии!E7*1000000*Допущения!C7)/Допущения!C7)*Допущения!C6)))>=Сценарии!E7*1000000*Допущения!C7,Сценарии!E7*1000000*Допущения!C7,MAX(0,MAX(0,Допущения!C5-Сценарии!E7*1000000*Допущения!C7)-IF(MAX(0,Допущения!C5-Сценарии!E7*1000000*Допущения!C7)=0,Сценарии!E7*1000000*Допущения!C6,IF(MAX(0,Допущения!C5-Сценарии!E7*1000000*Допущения!C7)>=Сценарии!E7*1000000*Допущения!C7,Сценарии!E7*1000000*Допущения!C7,MAX(0,Допущения!C5-Сценарии!E7*1000000*Допущения!C7)+(Сценарии!E7*1000000-MAX(0,Допущения!C5-Сценарии!E7*1000000*Допущения!C7)/Допущения!C7)*Допущения!C6)))+(Сценарии!E7*1000000-MAX(0,MAX(0,Допущения!C5-Сценарии!E7*1000000*Допущения!C7)-IF(MAX(0,Допущения!C5-Сценарии!E7*1000000*Допущения!C7)=0,Сценарии!E7*1000000*Допущения!C6,IF(MAX(0,Допущения!C5-Сценарии!E7*1000000*Допущения!C7)>=Сценарии!E7*1000000*Допущения!C7,Сценарии!E7*1000000*Допущения!C7,MAX(0,Допущения!C5-Сценарии!E7*1000000*Допущения!C7)+(Сценарии!E7*1000000-MAX(0,Допущения!C5-Сценарии!E7*1000000*Допущения!C7)/Допущения!C7)*Допущения!C6)))/Допущения!C7)*Допущения!C6)))*(C5/Допущения!C5)+Сценарии!E13*1000000*(C5/Допущения!C5) -> 3910154.5
B44: Кратность к вложению (×) | C44: =C43/C5 -> 2.7359364 | D44: =D43/C5 -> 3.3230455 | E44: =E43/C5 -> 3.9101545
B45: Вложено | C45: =C5 -> 1000000 | D45: =C5 -> 1000000 | E45: =C5 -> 1000000
B46: Чистый доход (total return − вложения) | C46: =(Сценарии!C7*1000000*Допущения!C7+IF(MAX(0,Допущения!C5-Сценарии!C7*1000000*Допущения!C7)=0,Сценарии!C7*1000000*Допущения!C6,IF(MAX(0,Допущения!C5-Сценарии!C7*1000000*Допущения!C7)>=Сценарии!C7*1000000*Допущения!C7,Сценарии!C7*1000000*Допущения!C7,MAX(0,Допущения!C5-Сценарии!C7*1000000*Допущения!C7)+(Сценарии!C7*1000000-MAX(0,Допущения!C5-Сценарии!C7*1000000*Допущения!C7)/Допущения!C7)*Допущения!C6))+IF(MAX(0,MAX(0,Допущения!C5-Сценарии!C7*1000000*Допущения!C7)-IF(MAX(0,Допущения!C5-Сценарии!C7*1000000*Допущения!C7)=0,Сценарии!C7*1000000*Допущения!C6,IF(MAX(0,Допущения!C5-Сценарии!C7*1000000*Допущения!C7)>=Сценарии!C7*1000000*Допущения!C7,Сценарии!C7*1000000*Допущения!C7,MAX(0,Допущения!C5-Сценарии!C7*1000000*Допущения!C7)+(Сценарии!C7*1000000-MAX(0,Допущения!C5-Сценарии!C7*1000000*Допущения!C7)/Допущения!C7)*Допущения!C6)))=0,Сценарии!C7*1000000*Допущения!C6,IF(MAX(0,MAX(0,Допущения!C5-Сценарии!C7*1000000*Допущения!C7)-IF(MAX(0,Допущения!C5-Сценарии!C7*1000000*Допущения!C7)=0,Сценарии!C7*1000000*Допущения!C6,IF(MAX(0,Допущения!C5-Сценарии!C7*1000000*Допущения!C7)>=Сценарии!C7*1000000*Допущения!C7,Сценарии!C7*1000000*Допущения!C7,MAX(0,Допущения!C5-Сценарии!C7*1000000*Допущения!C7)+(Сценарии!C7*1000000-MAX(0,Допущения!C5-Сценарии!C7*1000000*Допущения!C7)/Допущения!C7)*Допущения!C6)))>=Сценарии!C7*1000000*Допущения!C7,Сценарии!C7*1000000*Допущения!C7,MAX(0,MAX(0,Допущения!C5-Сценарии!C7*1000000*Допущения!C7)-IF(MAX(0,Допущения!C5-Сценарии!C7*1000000*Допущения!C7)=0,Сценарии!C7*1000000*Допущения!C6,IF(MAX(0,Допущения!C5-Сценарии!C7*1000000*Допущения!C7)>=Сценарии!C7*1000000*Допущения!C7,Сценарии!C7*1000000*Допущения!C7,MAX(0,Допущения!C5-Сценарии!C7*1000000*Допущения!C7)+(Сценарии!C7*1000000-MAX(0,Допущения!C5-Сценарии!C7*1000000*Допущения!C7)/Допущения!C7)*Допущения!C6)))+(Сценарии!C7*1000000-MAX(0,MAX(0,Допущения!C5-Сценарии!C7*1000000*Допущения!C7)-IF(MAX(0,Допущения!C5-Сценарии!C7*1000000*Допущения!C7)=0,Сценарии!C7*1000000*Допущения!C6,IF(MAX(0,Допущения!C5-Сценарии!C7*1000000*Допущения!C7)>=Сценарии!C7*1000000*Допущения!C7,Сценарии!C7*1000000*Допущения!C7,MAX(0,Допущения!C5-Сценарии!C7*1000000*Допущения!C7)+(Сценарии!C7*1000000-MAX(0,Допущения!C5-Сценарии!C7*1000000*Допущения!C7)/Допущения!C7)*Допущения!C6)))/Допущения!C7)*Допущения!C6)))*(C5/Допущения!C5)+Сценарии!C13*1000000*(C5/Допущения!C5)-C5 -> 1735936.4 | D46: =(Сценарии!D7*1000000*Допущения!C7+IF(MAX(0,Допущения!C5-Сценарии!D7*1000000*Допущения!C7)=0,Сценарии!D7*1000000*Допущения!C6,IF(MAX(0,Допущения!C5-Сценарии!D7*1000000*Допущения!C7)>=Сценарии!D7*1000000*Допущения!C7,Сценарии!D7*1000000*Допущения!C7,MAX(0,Допущения!C5-Сценарии!D7*1000000*Допущения!C7)+(Сценарии!D7*1000000-MAX(0,Допущения!C5-Сценарии!D7*1000000*Допущения!C7)/Допущения!C7)*Допущения!C6))+IF(MAX(0,MAX(0,Допущения!C5-Сценарии!D7*1000000*Допущения!C7)-IF(MAX(0,Допущения!C5-Сценарии!D7*1000000*Допущения!C7)=0,Сценарии!D7*1000000*Допущения!C6,IF(MAX(0,Допущения!C5-Сценарии!D7*1000000*Допущения!C7)>=Сценарии!D7*1000000*Допущения!C7,Сценарии!D7*1000000*Допущения!C7,MAX(0,Допущения!C5-Сценарии!D7*1000000*Допущения!C7)+(Сценарии!D7*1000000-MAX(0,Допущения!C5-Сценарии!D7*1000000*Допущения!C7)/Допущения!C7)*Допущения!C6)))=0,Сценарии!D7*1000000*Допущения!C6,IF(MAX(0,MAX(0,Допущения!C5-Сценарии!D7*1000000*Допущения!C7)-IF(MAX(0,Допущения!C5-Сценарии!D7*1000000*Допущения!C7)=0,Сценарии!D7*1000000*Допущения!C6,IF(MAX(0,Допущения!C5-Сценарии!D7*1000000*Допущения!C7)>=Сценарии!D7*1000000*Допущения!C7,Сценарии!D7*1000000*Допущения!C7,MAX(0,Допущения!C5-Сценарии!D7*1000000*Допущения!C7)+(Сценарии!D7*1000000-MAX(0,Допущения!C5-Сценарии!D7*1000000*Допущения!C7)/Допущения!C7)*Допущения!C6)))>=Сценарии!D7*1000000*Допущения!C7,Сценарии!D7*1000000*Допущения!C7,MAX(0,MAX(0,Допущения!C5-Сценарии!D7*1000000*Допущения!C7)-IF(MAX(0,Допущения!C5-Сценарии!D7*1000000*Допущения!C7)=0,Сценарии!D7*1000000*Допущения!C6,IF(MAX(0,Допущения!C5-Сценарии!D7*1000000*Допущения!C7)>=Сценарии!D7*1000000*Допущения!C7,Сценарии!D7*1000000*Допущения!C7,MAX(0,Допущения!C5-Сценарии!D7*1000000*Допущения!C7)+(Сценарии!D7*1000000-MAX(0,Допущения!C5-Сценарии!D7*1000000*Допущения!C7)/Допущения!C7)*Допущения!C6)))+(Сценарии!D7*1000000-MAX(0,MAX(0,Допущения!C5-Сценарии!D7*1000000*Допущения!C7)-IF(MAX(0,Допущения!C5-Сценарии!D7*1000000*Допущения!C7)=0,Сценарии!D7*1000000*Допущения!C6,IF(MAX(0,Допущения!C5-Сценарии!D7*1000000*Допущения!C7)>=Сценарии!D7*1000000*Допущения!C7,Сценарии!D7*1000000*Допущения!C7,MAX(0,Допущения!C5-Сценарии!D7*1000000*Допущения!C7)+(Сценарии!D7*1000000-MAX(0,Допущения!C5-Сценарии!D7*1000000*Допущения!C7)/Допущения!C7)*Допущения!C6)))/Допущения!C7)*Допущения!C6)))*(C5/Допущения!C5)+Сценарии!D13*1000000*(C5/Допущения!C5)-C5 -> 2323045.5 | E46: =(Сценарии!E7*1000000*Допущения!C7+IF(MAX(0,Допущения!C5-Сценарии!E7*1000000*Допущения!C7)=0,Сценарии!E7*1000000*Допущения!C6,IF(MAX(0,Допущения!C5-Сценарии!E7*1000000*Допущения!C7)>=Сценарии!E7*1000000*Допущения!C7,Сценарии!E7*1000000*Допущения!C7,MAX(0,Допущения!C5-Сценарии!E7*1000000*Допущения!C7)+(Сценарии!E7*1000000-MAX(0,Допущения!C5-Сценарии!E7*1000000*Допущения!C7)/Допущения!C7)*Допущения!C6))+IF(MAX(0,MAX(0,Допущения!C5-Сценарии!E7*1000000*Допущения!C7)-IF(MAX(0,Допущения!C5-Сценарии!E7*1000000*Допущения!C7)=0,Сценарии!E7*1000000*Допущения!C6,IF(MAX(0,Допущения!C5-Сценарии!E7*1000000*Допущения!C7)>=Сценарии!E7*1000000*Допущения!C7,Сценарии!E7*1000000*Допущения!C7,MAX(0,Допущения!C5-Сценарии!E7*1000000*Допущения!C7)+(Сценарии!E7*1000000-MAX(0,Допущения!C5-Сценарии!E7*1000000*Допущения!C7)/Допущения!C7)*Допущения!C6)))=0,Сценарии!E7*1000000*Допущения!C6,IF(MAX(0,MAX(0,Допущения!C5-Сценарии!E7*1000000*Допущения!C7)-IF(MAX(0,Допущения!C5-Сценарии!E7*1000000*Допущения!C7)=0,Сценарии!E7*1000000*Допущения!C6,IF(MAX(0,Допущения!C5-Сценарии!E7*1000000*Допущения!C7)>=Сценарии!E7*1000000*Допущения!C7,Сценарии!E7*1000000*Допущения!C7,MAX(0,Допущения!C5-Сценарии!E7*1000000*Допущения!C7)+(Сценарии!E7*1000000-MAX(0,Допущения!C5-Сценарии!E7*1000000*Допущения!C7)/Допущения!C7)*Допущения!C6)))>=Сценарии!E7*1000000*Допущения!C7,Сценарии!E7*1000000*Допущения!C7,MAX(0,MAX(0,Допущения!C5-Сценарии!E7*1000000*Допущения!C7)-IF(MAX(0,Допущения!C5-Сценарии!E7*1000000*Допущения!C7)=0,Сценарии!E7*1000000*Допущения!C6,IF(MAX(0,Допущения!C5-Сценарии!E7*1000000*Допущения!C7)>=Сценарии!E7*1000000*Допущения!C7,Сценарии!E7*1000000*Допущения!C7,MAX(0,Допущения!C5-Сценарии!E7*1000000*Допущения!C7)+(Сценарии!E7*1000000-MAX(0,Допущения!C5-Сценарии!E7*1000000*Допущения!C7)/Допущения!C7)*Допущения!C6)))+(Сценарии!E7*1000000-MAX(0,MAX(0,Допущения!C5-Сценарии!E7*1000000*Допущения!C7)-IF(MAX(0,Допущения!C5-Сценарии!E7*1000000*Допущения!C7)=0,Сценарии!E7*1000000*Допущения!C6,IF(MAX(0,Допущения!C5-Сценарии!E7*1000000*Допущения!C7)>=Сценарии!E7*1000000*Допущения!C7,Сценарии!E7*1000000*Допущения!C7,MAX(0,Допущения!C5-Сценарии!E7*1000000*Допущения!C7)+(Сценарии!E7*1000000-MAX(0,Допущения!C5-Сценарии!E7*1000000*Допущения!C7)/Допущения!C7)*Допущения!C6)))/Допущения!C7)*Допущения!C6)))*(C5/Допущения!C5)+Сценарии!E13*1000000*(C5/Допущения!C5)-C5 -> 2910154.5
B48: ℹ️ Механика расчёта: до полного возврата 66 млн ₽ всем инвесторам направляется 80% прибыли проекта, пропорционально долям вкладов. После полного возврата — 49% прибыли (совокупная доля инвесторов). Стоимость доли при продаже = прибыль × мультипликатор 3× × доля 49% × ваша пропорция. Все цифры рассчитываются автоматически на основе суммы в ячейке C5.

Sheet Дашборд
B1: LUCE SILVA — ИНВЕСТИЦИОННАЯ ФИНАНСОВАЯ МОДЕЛЬ
B2: Премиальная стеклянная оранжерея для свадеб | Москва и МО | 2027+
B3: Сценарий переключается на листе «Допущения» → ячейка C12 (1=Мин / 2=Базовый / 3=Макс)
B5: ПАРАМЕТРЫ ИНВЕСТИЦИЙ | D5: АКТИВНЫЙ СЦЕНАРИЙ
B6: Объём раунда | C6: =Допущения!C5 -> 66000000 | D6: Сценарий (1/2/3) | E6: =Допущения!C12 -> 2
B7: Доля инвестора | C7: =Допущения!C6 -> 0.49 | D7: Свадеб в сезон | E7: =Допущения!C13 -> 100
B8: Дивиденды до окупаемости | C8: =Допущения!C7 -> 0.8 | D8: Прибыль за сезон (млн ₽) | E8: =IF(Допущения!C12=1,Сценарии!C7,IF(Допущения!C12=2,Сценарии!D7,Сценарии!E7)) -> 65.9
B9: Мультипликатор оценки | C9: =Допущения!C9 -> 3 | D9: Инвестору (70%), млн ₽ | E9: =IF(Допущения!C12=1,Сценарии!C8,IF(Допущения!C12=2,Сценарии!D8,Сценарии!E8)) -> 52.72
B11: ЮНИТ-ЭКОНОМИКА ОДНОЙ СВАДЬБЫ | D11: CAPEX (66 МЛН ₽)
B12: Средний чек | C12: =Допущения!C21 -> 949000 | D12: Аренда земли | E12: =CAPEX!C4 -> 5000000
B13: Аренда площадки | C13: =Допущения!C22 -> 270000 | D13: Конструкция | E13: =CAPEX!C5 -> 22000000
B14: Кейтеринг | C14: =Допущения!C23 -> 604000 | D14: Инженерия | E14: =CAPEX!C6 -> 12000000
B15: Техника | C15: =Допущения!C24 -> 75000 | D15: Кухня | E15: =CAPEX!C7 -> 10000000
B16: COGS | C16: =Допущения!C25 -> 290000 | D16: Благоустройство | E16: =CAPEX!C8 -> 8000000
B17: Прибыль/свадьбу | C17: =Допущения!C26 -> 659000 | D17: Домик / хозблок | E17: =CAPEX!C9 -> 6000000
B18: Маржинальность | C18: =Допущения!C27 -> 0.69441517 | D18: Маркетинг и запуск | E18: =CAPEX!C10 -> 3000000
D19: ИТОГО CAPEX | E19: =CAPEX!C11 -> 66000000
B21: СРАВНЕНИЕ СЦЕНАРИЕВ
B22: Показатель | C22: МИН (75) | D22: БАЗОВЫЙ (100) | E22: МАКС (150)
B23: Прибыль сезон (млн) | C23: =Сценарии!C7 -> 52.72 | D23: =Сценарии!D7 -> 65.9 | E23: =Сценарии!E7 -> 79.08
B24: Инвестору 70% (млн) | C24: =Сценарии!C8 -> 42.176 | D24: =Сценарии!D8 -> 52.72 | E24: =Сценарии!E8 -> 63.264
B25: Доходность годовых | C25: =Сценарии!C9 -> 0.6390303 | D25: =Сценарии!D9 -> 0.79878788 | E25: =Сценарии!E9 -> 0.95854545
B26: Окупаемость (сезонов) | C26: =Сценарии!C10 -> 1.564871 | D26: =Сценарии!D10 -> 1.2518968 | E26: =Сценарии!E10 -> 1.0432473
B27: Оценка компании (млн) | C27: =Сценарии!C12 -> 158.16 | D27: =Сценарии!D12 -> 197.7 | E27: =Сценарии!E12 -> 237.24
B28: Доля 49% (млн) | C28: =Сценарии!C13 -> 77.4984 | D28: =Сценарии!D13 -> 96.873 | E28: =Сценарии!E13 -> 116.2476
B29: Total Return 3 сезона (млн) | C29: =Оценка!C15 -> 187.6832 | D29: =Оценка!D15 -> 234.604 | E29: =Оценка!E15 -> 281.5248
B30: Кратность к вложениям | C30: =Оценка!C16 -> 2.8436848 | D30: =Оценка!D16 -> 3.5546061 | E30: =Оценка!E16 -> 4.2655273
B32: УСЛОВНЫЕ ОБОЗНАЧЕНИЯ
B33: ■■■■■ | C33: Синий + голубой фон = исходные данные
B34: ■■■■■ | C34: Жёлтый фон = допущение аналитика (можно корректировать)
B35: ■■■■■ | C35: Зелёный текст = ссылка на другой лист
B36: ■■■■■ | C36: Чёрный текст = расчётная формула

Sheet Допущения
B1: ДОПУЩЕНИЯ И ВВОДНЫЕ — LUCE SILVA
B2: 🔵 Синий | 🟡 Жёлтый фон (допущение аналитика) | Ячейка C12 — переключатель сценария
C3: Значение | E3: Комментарий
B4: 1. ИНВЕСТИЦИОННЫЕ ПАРАМЕТРЫ
B5: Объём инвестиционного раунда | C5: 66000000
B6: Доля инвестора в компании | C6: 0.49
B7: Дивиденды до окупаемости (% прибыли) | C7: 0.8 | E7: Повышенная ставка до возврата
B8: Минимальный чек входа | C8: 1000000
B9: Мультипликатор оценки (x прибыли) | C9: 3
B11: 2. ВЫБОР СЦЕНАРИЯ
B12: Активный сценарий (1=Мин / 2=Базовый / 3=Макс) | C12: 2 | E12: ← МЕНЯЙТЕ ЗДЕСЬ для переключения сценария
B13: Свадеб в сезон (активный сценарий) | C13: =CHOOSE(C12,C16,C17,C18) -> 100 | E13: Автоматически по выбранному сценарию
B15: 3. СЦЕНАРИИ (свадеб в сезон,
B16: Минимальный сценарий | C16: 80 | E16: → прибыль ~52,7 млн ₽
B17: Базовый сценарий | C17: 100 | E17: → прибыль 50 млн ₽
B18: Максимальный сценарий | C18: 120 | E18: → прибыль ~79,1 млн ₽
B20: 4. ЮНИТ-ЭКОНОМИКА ОДНОЙ СВАДЬБЫ
B21: Средний чек (аренда + кейтеринг + техника) | C21: =C22+C23+C24 -> 949000 | E21: Автоматически: C22+C23+C24
B22: — Аренда площадки | C22: 270000 | E22: Средняя, июнь–сентябрь
B23: — Кейтеринг + сервисный сбор 15% | C23: 604000 | E23: 70 гостей: 525К + 15% сервисный сбор
B24: — Техника (свет, звук) | C24: 75000
B25: Переменная себестоимость (COGS) | C25: 290000 | E25: Продукты, персонал, логистика, налоги
B26: Прибыль с одной свадьбы | C26: =C21-C25 -> 659000 | E26: Выручка − COGS
B27: Маржинальность | C27: =C26/C21 -> 0.69441517 | E27: Прибыль / Выручка
B29: 5. СЕЗОННОСТЬ — ДОЛЯ СВАДЕБ ПО МЕСЯЦАМ
B30: Сезон май–октябрь. Помесячное распределение — допущение аналитика.
B31: Январь | C31: 0 | E31: Вне сезона
B32: Февраль | C32: 0 | E32: Вне сезона
B33: Март | C33: 0 | E33: Вне сезона
B34: Апрель | C34: 0 | E34: Вне сезона
B35: Май | C35: 0.15 | E35: [ASSUMPTION] типичный профиль свадебного сезона
B36: Июнь | C36: 0.2 | E36: [ASSUMPTION] типичный профиль свадебного сезона
B37: Июль | C37: 0.15 | E37: [ASSUMPTION] типичный профиль свадебного сезона
B38: Август | C38: 0.15 | E38: [ASSUMPTION] типичный профиль свадебного сезона
B39: Сентябрь | C39: 0.25 | E39: [ASSUMPTION] типичный профиль свадебного сезона
B40: Октябрь | C40: 0.1 | E40: [ASSUMPTION] типичный профиль свадебного сезона
B41: Ноябрь | C41: 0 | E41: Вне сезона
B42: Декабрь | C42: 0 | E42: Вне сезона
B43: ИТОГО (должно = 100%) | C43: =SUM(C31:C42) -> 1 | E43: Контроль: если ≠ 100%, пересмотрите распределение
B45: 6. ОПЕРАЦИОННЫЕ ДОПУЩЕНИЯ АНАЛИТИКА [НЕ
B46: Параметры ниже отсутствуют в презентации. Помечены [ASSUMPTION]. Можно корректировать.
B47: Год 1: исполнение плана (рамп-ап) | C47: 0.8 | E47: [ASSUMPTION] 80% в первый сезон
B48: Год 2: исполнение плана | C48: 0.9 | E48: [ASSUMPTION] 90% во второй сезон
B49: Год 3: исполнение плана | C49: 1 | E49: [ASSUMPTION] 100% (стабильный режим)
B50: Рост среднего чека год к году | C50: 0.08 | E50: [ASSUMPTION] инфляция + апселл
B51: Фикс. расходы: вне сезона (мес.) | C51: 300000 | E51: [ASSUMPTION] охрана, коммуналка, адм.
B52: Фикс. расходы: в сезон, доп. (мес.) | C52: 200000 | E52: [ASSUMPTION] управленческие сверх COGS
B53: Аренда земли в год (5 млн / 10 лет) | C53: 500000 | E53: [ASSUMPTION] = C5_CAPEX_land / 10
B54: Амортизация CAPEX в год (÷7 лет) | C54: 9428571 | E54: [ASSUMPTION] = 66 000 000 / 7

Sheet CAPEX
B1: CAPEX — ИНВЕСТИЦИОННЫЙ БЮДЖЕТ
B3: СТАТЬЯ CAPEX | C3: СУММА, ₽ | D3: ДОЛЯ | E3: КОММЕНТАРИЙ
B4: Аренда земли (10 лет, 1 га) | C4: 5000000 | D4: =C4/C11 -> 0.075757576 | E4: Предоплата за 10-летний договор
B5: Конструкция (стеклянная оранжерея) | C5: 22000000 | D5: =C5/C11 -> 0.33333333 | E5: Каркас, стекло, фундамент, кровля
B6: Инженерные системы | C6: 12000000 | D6: =C6/C11 -> 0.18181818 | E6: Электрика, тепло, вентиляция, водоснабжение
B7: Кухонное оборудование | C7: 10000000 | D7: =C7/C11 -> 0.15151515 | E7: Профессиональная кухня — собственный кейтеринг
B8: Благоустройство территории | C8: 8000000 | D8: =C8/C11 -> 0.12121212 | E8: Настил, освещение, ландшафт, парковка
B9: Домик / хозблок | C9: 6000000 | D9: =C9/C11 -> 0.090909091 | E9: Гостевой домик: 15 тыс ₽/сутки — доп. доход
B10: Маркетинг и запуск | C10: 3000000 | D10: =C10/C11 -> 0.045454545 | E10: Бренд, съёмки, SMM, открытие
B11: ИТОГО CAPEX | C11: =SUM(C4:C10) -> 66000000 | D11: 1
B13: ПРОВЕРКА: сумма должна = 66 000 000 ₽
B14: Итого CAPEX | C14: =C11 -> 66000000
B15: Целевой раунд | C15: =Допущения!C5 -> 66000000
B16: Разница (должна быть 0) | C16: =C11-Допущения!C5 -> 0
B18: РАСПРЕДЕЛЕНИЕ ПО СТАТЬЯМ
B19: Строительство + инженерия | C19: =C5+C6 -> 34000000
B20: Кухня + оборудование | C20: =C7 -> 10000000
B21: Благоустройство + домик | C21: =C8+C9 -> 14000000
B22: Земля + маркетинг | C22: =C4+C10 -> 8000000

Sheet Юнит-экономика
B1: ЮНИТ-ЭКОНОМИКА — ОДНА СВАДЬБА
B3: ВЫРУЧКА С ОДНОЙ СВАДЬБЫ (Источник: презентация)
B4: СТАТЬЯ | C4: СУММА | D4: % ВЫРУЧКИ | E4: ИСТОЧНИК
B5: Аренда площадки | C5: =Допущения!C22 -> 270000 | D5: =C5/Допущения!C21 -> 0.28451001
B6: Кейтеринг (собственная кухня) | C6: =Допущения!C23 -> 604000 | D6: =C6/Допущения!C21 -> 0.63645943
B7: Техника (свет, звук) | C7: =Допущения!C24 -> 75000 | D7: =C7/Допущения!C21 -> 0.079030558
B8: ИТОГО ВЫРУЧКА | C8: =Допущения!C21 -> 949000 | D8: =C8/C8 -> 1
B10: ПЕРЕМЕННЫЕ РАСХОДЫ (COGS) НА ОДНУ СВАДЬБУ
B11: СТАТЬЯ | C11: СУММА | D11: % ВЫРУЧКИ | E11: ПРИМЕЧАНИЕ
B12: Продукты и напитки | C12: 90000 | D12: =C12/Допущения!C21 -> 0.09483667 | E12: [ASSUMPTION] ~22% от выручки
B13: Персонал мероприятия | C13: 55000 | D13: =C13/Допущения!C21 -> 0.057955743 | E13: [ASSUMPTION] повара, официанты
B14: Логистика и клининг | C14: 30000 | D14: =C14/Допущения!C21 -> 0.031612223 | E14: [ASSUMPTION] доставка, уборка
B15: Охрана и коммунальные (event) | C15: 20000 | D15: =C15/Допущения!C21 -> 0.021074816 | E15: [ASSUMPTION] переменная часть
B16: Налоги и прочее | C16: 30000 | D16: =C16/Допущения!C21 -> 0.031612223 | E16: [ASSUMPTION] расчётная
B17: Итого по статьям (расчёт) | C17: =SUM(C12:C16) -> 225000 | D17: =C17/Допущения!C21 -> 0.23709168
B18: ИТОГО COGS | C18: =Допущения!C25 -> 290000 | D18: =C18/Допущения!C21 -> 0.30558483
B19: Разница (доп. COGS к распределению) | C19: =Допущения!C25-SUM(C12:C16) -> 65000
B21: P&L ОДНОЙ СВАДЬБЫ
B22: ПОКАЗАТЕЛЬ | C22: СУММА | D22: МАРЖА | E22: ИСТОЧНИК
B23: Выручка (средний чек) | C23: =Допущения!C21 -> 949000 | D23: =C23/C23 -> 1
B24: Переменная себестоимость | C24: =Допущения!C25 -> 290000 | D24: =C24/C23 -> 0.30558483
B25: ОПЕРАЦИОННАЯ ПРИБЫЛЬ | C25: =Допущения!C26 -> 659000 | D25: =C25/C23 -> 0.69441517 | E25: Выручка − COGS
B27: КОНТРОЛЬНЫЕ ЗНАЧЕНИЯ
B28: ПОКАЗАТЕЛЬ | C28: ПЛАН (презент.) | D28: МОДЕЛЬ | E28: СТАТУС
B29: Выручка | C29: 949000 | D29: =Допущения!C21 -> 949000 | E29: =IF(C29=D29,"✓ СОВПАДАЕТ","⚠ ПРОВЕРИТЬ") -> ✓ СОВПАДАЕТ
B30: COGS | C30: 290000 | D30: =Допущения!C25 -> 290000 | E30: =IF(C30=D30,"✓ СОВПАДАЕТ","⚠ ПРОВЕРИТЬ") -> ✓ СОВПАДАЕТ
B31: Прибыль | C31: 659000 | D31: =Допущения!C26 -> 659000 | E31: =IF(C31=D31,"✓ СОВПАДАЕТ","⚠ ПРОВЕРИТЬ") -> ✓ СОВПАДАЕТ

Sheet P&L 36 мес
B1: P&L — ПОМЕСЯЧНАЯ ФИНАНСОВАЯ МОДЕЛЬ (36 МЕСЯЦЕВ)
B2: Год / Месяц | C2: 2027 | D2: 2027 | E2: 2027 | F2: 2027 | G2: 2027 | H2: 2027 | I2: 2027 | J2: 2027 | K2: 2028 | L2: 2028 | M2: 2028 | N2: 2028 | O2: 2028 | P2: 2028 | Q2: 2028 | R2: 2028 | S2: 2028 | T2: 2028 | U2: 2028 | V2: 2028 | W2: 2029 | X2: 2029 | Y2: 2029 | Z2: 2029 | AA2: 2029 | AB2: 2029 | AC2: 2029 | AD2: 2029 | AE2: 2029 | AF2: 2029 | AG2: 2029 | AH2: 2029 | AI2: 2030 | AJ2: 2030 | AK2: 2030 | AL2: 2030 | AM2: Год 1 2027 | AN2: Год 2 2028 | AO2: Год 3 2029
B3: Показатель | C3: Май | D3: Июн | E3: Июл | F3: Авг | G3: Сен | H3: Окт | I3: Ноя | J3: Дек | K3: Янв | L3: Фев | M3: Мар | N3: Апр | O3: Май | P3: Июн | Q3: Июл | R3: Авг | S3: Сен | T3: Окт | U3: Ноя | V3: Дек | W3: Янв | X3: Фев | Y3: Мар | Z3: Апр | AA3: Май | AB3: Июн | AC3: Июл | AD3: Авг | AE3: Сен | AF3: Окт | AG3: Ноя | AH3: Дек | AI3: Янв | AJ3: Фев | AK3: Мар | AL3: Апр
B4: ВЫРУЧКА
B5: Количество свадеб | C5: =ROUND(Допущения!C13*Допущения!C35*Допущения!C47,0) -> 12 | D5: =ROUND(Допущения!C13*Допущения!C36*Допущения!C47,0) -> 16 | E5: =ROUND(Допущения!C13*Допущения!C37*Допущения!C47,0) -> 12 | F5: =ROUND(Допущения!C13*Допущения!C38*Допущения!C47,0) -> 12 | G5: =ROUND(Допущения!C13*Допущения!C39*Допущения!C47,0) -> 20 | H5: =ROUND(Допущения!C13*Допущения!C40*Допущения!C47,0) -> 8 | I5: 0 | J5: 0 | K5: 0 | L5: 0 | M5: 0 | N5: 0 | O5: =ROUND(Допущения!C13*Допущения!C35*Допущения!C48,0) -> 14 | P5: =ROUND(Допущения!C13*Допущения!C36*Допущения!C48,0) -> 18 | Q5: =ROUND(Допущения!C13*Допущения!C37*Допущения!C48,0) -> 14 | R5: =ROUND(Допущения!C13*Допущения!C38*Допущения!C48,0) -> 14 | S5: =ROUND(Допущения!C13*Допущения!C39*Допущения!C48,0) -> 23 | T5: =ROUND(Допущения!C13*Допущения!C40*Допущения!C48,0) -> 9 | U5: 0 | V5: 0 | W5: 0 | X5: 0 | Y5: 0 | Z5: 0 | AA5: =ROUND(Допущения!C13*Допущения!C35*Допущения!C49,0) -> 15 | AB5: =ROUND(Допущения!C13*Допущения!C36*Допущения!C49,0) -> 20 | AC5: =ROUND(Допущения!C13*Допущения!C37*Допущения!C49,0) -> 15 | AD5: =ROUND(Допущения!C13*Допущения!C38*Допущения!C49,0) -> 15 | AE5: =ROUND(Допущения!C13*Допущения!C39*Допущения!C49,0) -> 25 | AF5: =ROUND(Допущения!C13*Допущения!C40*Допущения!C49,0) -> 10 | AG5: 0 | AH5: 0 | AI5: 0 | AJ5: 0 | AK5: 0 | AL5: 0 | AM5: =SUM(C5:N5) -> 80 | AN5: =SUM(O5:Z5) -> 92 | AO5: =SUM(AA5:AL5) -> 100
B6: Выручка (₽) | C6: =C5*Допущения!C21*(1+Допущения!C50)^1 -> 12299040 | D6: =D5*Допущения!C21*(1+Допущения!C50)^1 -> 16398720 | E6: =E5*Допущения!C21*(1+Допущения!C50)^1 -> 12299040 | F6: =F5*Допущения!C21*(1+Допущения!C50)^1 -> 12299040 | G6: =G5*Допущения!C21*(1+Допущения!C50)^1 -> 20498400 | H6: =H5*Допущения!C21*(1+Допущения!C50)^1 -> 8199360 | I6: 0 | J6: 0 | K6: 0 | L6: 0 | M6: 0 | N6: 0 | O6: =O5*Допущения!C21*(1+Допущения!C50)^2 -> 15496790 | P6: =P5*Допущения!C21*(1+Допущения!C50)^2 -> 19924445 | Q6: =Q5*Допущения!C21*(1+Допущения!C50)^2 -> 15496790 | R6: =R5*Допущения!C21*(1+Допущения!C50)^2 -> 15496790 | S6: =S5*Допущения!C21*(1+Допущения!C50)^2 -> 25459013 | T6: =T5*Допущения!C21*(1+Допущения!C50)^2 -> 9962222.4 | U6: 0 | V6: 0 | W6: 0 | X6: 0 | Y6: 0 | Z6: 0 | AA6: =AA5*Допущения!C21*(1+Допущения!C50)^3 -> 17932000 | AB6: =AB5*Допущения!C21*(1+Допущения!C50)^3 -> 23909334 | AC6: =AC5*Допущения!C21*(1+Допущения!C50)^3 -> 17932000 | AD6: =AD5*Допущения!C21*(1+Допущения!C50)^3 -> 17932000 | AE6: =AE5*Допущения!C21*(1+Допущения!C50)^3 -> 29886667 | AF6: =AF5*Допущения!C21*(1+Допущения!C50)^3 -> 11954667 | AG6: 0 | AH6: 0 | AI6: 0 | AJ6: 0 | AK6: 0 | AL6: 0 | AM6: =SUM(C6:N6) -> 81993600 | AN6: =SUM(O6:Z6) -> 1.0183605e+08 | AO6: =SUM(AA6:AL6) -> 1.1954667e+08
B7: COGS переменные (₽) | C7: =C5*Допущения!C25 -> 3480000 | D7: =D5*Допущения!C25 -> 4640000 | E7: =E5*Допущения!C25 -> 3480000 | F7: =F5*Допущения!C25 -> 3480000 | G7: =G5*Допущения!C25 -> 5800000 | H7: =H5*Допущения!C25 -> 2320000 | I7: 0 | J7: 0 | K7: 0 | L7: 0 | M7: 0 | N7: 0 | O7: =O5*Допущения!C25 -> 4060000 | P7: =P5*Допущения!C25 -> 5220000 | Q7: =Q5*Допущения!C25 -> 4060000 | R7: =R5*Допущения!C25 -> 4060000 | S7: =S5*Допущения!C25 -> 6670000 | T7: =T5*Допущения!C25 -> 2610000 | U7: 0 | V7: 0 | W7: 0 | X7: 0 | Y7: 0 | Z7: 0 | AA7: =AA5*Допущения!C25 -> 4350000 | AB7: =AB5*Допущения!C25 -> 5800000 | AC7: =AC5*Допущения!C25 -> 4350000 | AD7: =AD5*Допущения!C25 -> 4350000 | AE7: =AE5*Допущения!C25 -> 7250000 | AF7: =AF5*Допущения!C25 -> 2900000 | AG7: 0 | AH7: 0 | AI7: 0 | AJ7: 0 | AK7: 0 | AL7: 0 | AM7: =SUM(C7:N7) -> 23200000 | AN7: =SUM(O7:Z7) -> 26680000 | AO7: =SUM(AA7:AL7) -> 29000000
B8: ВАЛОВАЯ ПРИБЫЛЬ (₽) | C8: =C6-C7 -> 8819040 | D8: =D6-D7 -> 11758720 | E8: =E6-E7 -> 8819040 | F8: =F6-F7 -> 8819040 | G8: =G6-G7 -> 14698400 | H8: =H6-H7 -> 5879360 | I8: =I6-I7 -> 0 | J8: =J6-J7 -> 0 | ... AO8: =AO6-AO7 -> 90546669
B9: Маржа валовой прибыли (%) | C9: =IFERROR(IF(C6=0,0,C8/C6),0) -> 0.71705109 | D9: =IFERROR(IF(D6=0,0,D8/D6),0) -> 0.71705109 | E9: =IFERROR(IF(E6=0,0,E8/E6),0) -> 0.71705109 | F9: =IFERROR(IF(F6=0,0,F8/F6),0) -> 0.71705109 | G9: =IFERROR(IF(G6=0,0,G8/G6),0) -> 0.71705109 | H9: =IFERROR(IF(H6=0,0,H8/H6),0) -> 0.71705109 | I9: =IFERROR(IF(I6=0,0,I8/I6),0) -> 0 | J9: =IFERROR(IF(J6=0,0,J8/J6),0) -> 0 | ... AO9: =IFERROR(IF(AO6=0,0,AO8/AO6),0) -> 0.75741691
B10: ПОСТОЯННЫЕ РАСХОДЫ
B11: Фиксированные расходы (₽) | C11: =Допущения!C52+Допущения!C53/12 -> 241666.67 | D11: =Допущения!C52+Допущения!C53/12 -> 241666.67 | E11: =Допущения!C52+Допущения!C53/12 -> 241666.67 | F11: =Допущения!C52+Допущения!C53/12 -> 241666.67 | G11: =Допущения!C52+Допущения!C53/12 -> 241666.67 | H11: =Допущения!C52+Допущения!C53/12 -> 241666.67 | I11: =Допущения!C51+Допущения!C53/12 -> 341666.67 | J11: =Допущения!C51+Допущения!C53/12 -> 341666.67 | K11: =Допущения!C51+Допущения!C53/12 -> 341666.67 | L11: =Допущения!C51+Допущения!C53/12 -> 341666.67 | M11: =Допущения!C51+Допущения!C53/12 -> 341666.67 | N11: =Допущения!C51+Допущения!C53/12 -> 341666.67 | O11: =Допущения!C52+Допущения!C53/12 -> 241666.67 | P11: =Допущения!C52+Допущения!C53/12 -> 241666.67 | Q11: =Допущения!C52+Допущения!C53/12 -> 241666.67 | R11: =Допущения!C52+Допущения!C53/12 -> 241666.67 | S11: =Допущения!C52+Допущения!C53/12 -> 241666.67 | T11: =Допущения!C52+Допущения!C53/12 -> 241666.67 | U11: =Допущения!C51+Допущения!C53/12 -> 341666.67 | V11: =Допущения!C51+Допущения!C53/12 -> 341666.67 | W11: =Допущения!C51+Допущения!C53/12 -> 341666.67 | X11: =Допущения!C51+Допущения!C53/12 -> 341666.67 | Y11: =Допущения!C51+Допущения!C53/12 -> 341666.67 | Z11: =Допущения!C51+Допущения!C53/12 -> 341666.67 | AA11: =Допущения!C52+Допущения!C53/12 -> 241666.67 | AB11: =Допущения!C52+Допущения!C53/12 -> 241666.67 | AC11: =Допущения!C52+Допущения!C53/12 -> 241666.67 | AD11: =Допущения!C52+Допущения!C53/12 -> 241666.67 | AE11: =Допущения!C52+Допущения!C53/12 -> 241666.67 | AF11: =Допущения!C52+Допущения!C53/12 -> 241666.67 | AG11: =Допущения!C51+Допущения!C53/12 -> 341666.67 | AH11: =Допущения!C51+Допущения!C53/12 -> 341666.67 | AI11: =Допущения!C51+Допущения!C53/12 -> 341666.67 | AJ11: =Допущения!C51+Допущения!C53/12 -> 341666.67 | AK11: =Допущения!C51+Допущения!C53/12 -> 341666.67 | AL11: =Допущения!C51+Допущения!C53/12 -> 341666.67 | AM11: =SUM(C11:N11) -> 3500000 | AN11: =SUM(O11:Z11) -> 3500000 | AO11: =SUM(AA11:AL11) -> 3500000
B12: EBITDA (₽) | C12: =C8-C11 -> 8577373.3 | D12: =D8-D11 -> 11517053 | E12: =E8-E11 -> 8577373.3 | F12: =F8-F11 -> 8577373.3 | G12: =G8-G11 -> 14456733 | H12: =H8-H11 -> 5637693.3 | I12: =I8-I11 -> -341666.67 | J12: =J8-J11 -> -341666.67 | ... AO12: =AO8-AO11 -> 87046669
B13: Амортизация (₽) | C13: =Допущения!C54/12 -> 785714.25 | D13: =Допущения!C54/12 -> 785714.25 | E13: =Допущения!C54/12 -> 785714.25 | F13: =Допущения!C54/12 -> 785714.25 | G13: =Допущения!C54/12 -> 785714.25 | H13: =Допущения!C54/12 -> 785714.25 | I13: =Допущения!C54/12 -> 785714.25 | J13: =Допущения!C54/12 -> 785714.25 | K13: =Допущения!C54/12 -> 785714.25 | L13: =Допущения!C54/12 -> 785714.25 | M13: =Допущения!C54/12 -> 785714.25 | N13: =Допущения!C54/12 -> 785714.25 | O13: =Допущения!C54/12 -> 785714.25 | P13: =Допущения!C54/12 -> 785714.25 | Q13: =Допущения!C54/12 -> 785714.25 | R13: =Допущения!C54/12 -> 785714.25 | S13: =Допущения!C54/12 -> 785714.25 | T13: =Допущения!C54/12 -> 785714.25 | U13: =Допущения!C54/12 -> 785714.25 | V13: =Допущения!C54/12 -> 785714.25 | W13: =Допущения!C54/12 -> 785714.25 | X13: =Допущения!C54/12 -> 785714.25 | Y13: =Допущения!C54/12 -> 785714.25 | Z13: =Допущения!C54/12 -> 785714.25 | AA13: =Допущения!C54/12 -> 785714.25 | AB13: =Допущения!C54/12 -> 785714.25 | AC13: =Допущения!C54/12 -> 785714.25 | AD13: =Допущения!C54/12 -> 785714.25 | AE13: =Допущения!C54/12 -> 785714.25 | AF13: =Допущения!C54/12 -> 785714.25 | AG13: =Допущения!C54/12 -> 785714.25 | AH13: =Допущения!C54/12 -> 785714.25 | AI13: =Допущения!C54/12 -> 785714.25 | AJ13: =Допущения!C54/12 -> 785714.25 | AK13: =Допущения!C54/12 -> 785714.25 | AL13: =Допущения!C54/12 -> 785714.25 | AM13: =SUM(C13:N13) -> 9428571 | AN13: =SUM(O13:Z13) -> 9428571 | AO13: =SUM(AA13:AL13) -> 9428571
B14: EBIT / Чистая прибыль (₽) | C14: =C12-C13 -> 7791659.1 | D14: =D12-D13 -> 10731339 | E14: =E12-E13 -> 7791659.1 | F14: =F12-F13 -> 7791659.1 | G14: =G12-G13 -> 13671019 | H14: =H12-H13 -> 4851979.1 | I14: =I12-I13 -> -1127380.9 | J14: =J12-J13 -> -1127380.9 | ... AO14: =AO12-AO13 -> 77618098
B15: Дивиденды инвестору (70% от прибыли) | C15: =MAX(0,C14)*Допущения!C7 -> 6233327.3 | D15: =MAX(0,D14)*Допущения!C7 -> 8585071.3 | E15: =MAX(0,E14)*Допущения!C7 -> 6233327.3 | F15: =MAX(0,F14)*Допущения!C7 -> 6233327.3 | G15: =MAX(0,G14)*Допущения!C7 -> 10936815 | H15: =MAX(0,H14)*Допущения!C7 -> 3881583.3 | I15: =MAX(0,I14)*Допущения!C7 -> 0 | J15: =MAX(0,J14)*Допущения!C7 -> 0 | K15: =MAX(0,K14)*Допущения!C7 -> 0 | L15: =MAX(0,L14)*Допущения!C7 -> 0 | M15: =MAX(0,M14)*Допущения!C7 -> 0 | N15: =MAX(0,N14)*Допущения!C7 -> 0 | O15: =MAX(0,O14)*Допущения!C7 -> 8327527.6 | P15: =MAX(0,P14)*Допущения!C7 -> 10941651 | Q15: =MAX(0,Q14)*Допущения!C7 -> 8327527.6 | R15: =MAX(0,R14)*Допущения!C7 -> 8327527.6 | S15: =MAX(0,S14)*Допущения!C7 -> 14209306 | T15: =MAX(0,T14)*Допущения!C7 -> 5059873.2 | U15: =MAX(0,U14)*Допущения!C7 -> 0 | V15: =MAX(0,V14)*Допущения!C7 -> 0 | W15: =MAX(0,W14)*Допущения!C7 -> 0 | X15: =MAX(0,X14)*Допущения!C7 -> 0 | Y15: =MAX(0,Y14)*Допущения!C7 -> 0 | Z15: =MAX(0,Z14)*Допущения!C7 -> 0 | AA15: =MAX(0,AA14)*Допущения!C7 -> 10043696 | AB15: =MAX(0,AB14)*Допущения!C7 -> 13665562 | AC15: =MAX(0,AC14)*Допущения!C7 -> 10043696 | AD15: =MAX(0,AD14)*Допущения!C7 -> 10043696 | AE15: =MAX(0,AE14)*Допущения!C7 -> 17287429 | AF15: =MAX(0,AF14)*Допущения!C7 -> 6421828.8 | AG15: =MAX(0,AG14)*Допущения!C7 -> 0 | AH15: =MAX(0,AH14)*Допущения!C7 -> 0 | AI15: =MAX(0,AI14)*Допущения!C7 -> 0 | AJ15: =MAX(0,AJ14)*Допущения!C7 -> 0 | AK15: =MAX(0,AK14)*Допущения!C7 -> 0 | AL15: =MAX(0,AL14)*Допущения!C7 -> 0 | AM15: =MAX(0,AM14)*Допущения!C7 -> 36692023 | AN15: =MAX(0,AN14)*Допущения!C7 -> 49781984 | AO15: =MAX(0,AO14)*Допущения!C7 -> 62094478
B16: Прибыль проекта (после инвестора) | C16: =C14-C15 -> 1558331.8 | D16: =D14-D15 -> 2146267.8 | E16: =E14-E15 -> 1558331.8 | F16: =F14-F15 -> 1558331.8 | G16: =G14-G15 -> 2734203.8 | H16: =H14-H15 -> 970395.82 | I16: =I14-I15 -> -1127380.9 | J16: =J14-J15 -> -1127380.9 | ... AO16: =AO14-AO15 -> 15523620

Sheet Сценарии
B1: АНАЛИЗ СЦЕНАРИЕВ — LUCE SILVA
B2: ПОКАЗАТЕЛЬ | C2: МИН (80 свадеб) | D2: БАЗОВЫЙ (100 свадеб) | E2: МАКС (120 свадеб)
B3: ОСНОВНАЯ СЕЗОННАЯ ЭКОНОМИКА (Источник: презентация)
B4: Свадеб в сезон | C4: =Допущения!C16 -> 80 | D4: =Допущения!C17 -> 100 | E4: =Допущения!C18 -> 120
B5: Выручка за сезон | C5: =Допущения!C16*Допущения!C21/1000000 -> 75.92 | D5: =Допущения!C17*Допущения!C21/1000000 -> 94.9 | E5: =Допущения!C18*Допущения!C21/1000000 -> 113.88
B6: Переменные расходы за сезон | C6: =Допущения!C16*Допущения!C25/1000000 -> 23.2 | D6: =Допущения!C17*Допущения!C25/1000000 -> 29 | E6: =Допущения!C18*Допущения!C25/1000000 -> 34.8
B7: ПРИБЫЛЬ ПРОЕКТА ЗА СЕЗОН | C7: =Допущения!C16*Допущения!C26/1000000 -> 52.72 | D7: =Допущения!C17*Допущения!C26/1000000 -> 65.9 | E7: =Допущения!C18*Допущения!C26/1000000 -> 79.08
B8: Инвестору (70% до окупаемости) | C8: =C7*Допущения!C7 -> 42.176 | D8: =D7*Допущения!C7 -> 52.72 | E8: =E7*Допущения!C7 -> 63.264
B9: Доходность годовых (=инвестору/инвестиции) | C9: =C8*1000000/Допущения!C5 -> 0.6390303 | D9: =D8*1000000/Допущения!C5 -> 0.79878788 | E9: =E8*1000000/Допущения!C5 -> 0.95854545
B10: Окупаемость (кол-во сезонов) | C10: =Допущения!C5/(C8*1000000) -> 1.564871 | D10: =Допущения!C5/(D8*1000000) -> 1.2518968 | E10: =Допущения!C5/(E8*1000000) -> 1.0432473
B11: ОЦЕНКА КОМПАНИИ (мультипликатор 3x прибыли)
B12: Оценка компании (прибыль × 3x) | C12: =C7*Допущения!C9 -> 158.16 | D12: =D7*Допущения!C9 -> 197.7 | E12: =E7*Допущения!C9 -> 237.24
B13: Стоимость доли инвестора (49%) | C13: =C12*Допущения!C6 -> 77.4984 | D13: =D12*Допущения!C6 -> 96.873 | E13: =E12*Допущения!C6 -> 116.2476
B15: ПРЕЗЕНТАЦИОННЫЕ ОРИЕНТИРЫ ДЛЯ СВЕРКИ
B16: ПОКАЗАТЕЛЬ | C16: МИН | D16: БАЗОВЫЙ | E16: МАКС
B17: Прибыль сезон (млн) — план | C17: 37.5 | D17: 50 | E17: 75
B18: Инвестору 70% (млн) — план | C18: 26.25 | D18: 35 | E18: 52.5
B19: Доходность годовых — план | C19: 0.398 | D19: 0.53 | E19: 0.795
B20: Окупаемость (сезонов) — план | C20: 2.5 | D20: 2 | E20: 1.25
B21: Оценка (млн) — план | C21: 112.5 | D21: 150 | E21: 225
B22: Доля 49% (млн) — план | C22: 55.125 | D22: 73.5 | E22: 110.25
B24: СРАВНЕНИЕ МОДЕЛИ С ПЛАНОМ
B25: ПОКАЗАТЕЛЬ | C25: МИН ΔДЕЛЬТА | D25: БАЗ ΔДЕЛЬТА | E25: МАКС ΔДЕЛЬТА
B26: Прибыль сезон — отклонение (модель − план) | C26: =C7-C17 -> 15.22 | D26: =D7-D17 -> 15.9 | E26: =E7-E17 -> 4.08
B27: Инвестору 70% — отклонение | C27: =C8-C18 -> 15.926 | D27: =D8-D18 -> 17.72 | E27: =E8-E18 -> 10.764

Sheet Инвестор
B1: КАЛЬКУЛЯТОР ДОХОДНОСТИ ИНВЕСТОРА — LUCE SILVA
B2: 🟡 Ячейки с жёлтым фоном — меняйте сами | Сценарий переключается в листе «Допущения» (ячейка C12)
B4: ПАРАМЕТРЫ ИНВЕСТОРА
B5: Ваша сумма инвестиций, ₽ | C5: 1000000 | D5: Введите свою сумму
B6: Ваша доля в компании (%) | C6: =C5/Допущения!C5*Допущения!C6 -> 0.0074242424 | D6: ваши деньги / 66 млн × 49%
B7: Минимальный чек входа | C7: =Допущения!C8 -> 1000000
B9: ВАШИ ДИВИДЕНДЫ ПО СЦЕНАРИЯМ (ЗА 1 СЕЗОН)
B10: ПОКАЗАТЕЛЬ | C10: МИН | D10: БАЗОВЫЙ | E10: МАКС
B11: Прибыль проекта (млн ₽) | C11: =Сценарии!C7 -> 52.72 | D11: =Сценарии!D7 -> 65.9 | E11: =Сценарии!E7 -> 79.08
B12: Ваша доля в дивидендах (70%) — ваши ₽ | C12: =C11*1000000*Допущения!C7*(C5/Допущения!C5) -> 639030.3 | D12: =D11*1000000*Допущения!C7*(C5/Допущения!C5) -> 798787.88 | E12: =E11*1000000*Допущения!C7*(C5/Допущения!C5) -> 958545.45
B13: Доходность за 1 сезон | C13: =C12/C5 -> 0.6390303 | D13: =D12/C5 -> 0.79878788 | E13: =E12/C5 -> 0.95854545
B14: Окупаемость (сезонов) | C14: =C5/C12 -> 1.564871 | D14: =C5/D12 -> 1.2518968 | E14: =C5/E12 -> 1.0432473
B16: ДИВИДЕНДНЫЙ ПОТОК — 3 СЕЗОНА
B17: ПОКАЗАТЕЛЬ | C17: МИН | D17: БАЗОВЫЙ | E17: МАКС
B18: СЕЗОН 1 — прибыль проекта (млн ₽) | C18: =Сценарии!C7 -> 52.72 | D18: =Сценарии!D7 -> 65.9 | E18: =Сценарии!E7 -> 79.08
B19: Инвестору (70%) | C19: =C18*Допущения!C7 -> 42.176 | D19: =D18*Допущения!C7 -> 52.72 | E19: =E18*Допущения!C7 -> 63.264
B20: Остаток долга к погашению | C20: =MAX(0,Допущения!C5/1000000-C19) -> 23.824 | D20: =MAX(0,Допущения!C5/1000000-D19) -> 13.28 | E20: =MAX(0,Допущения!C5/1000000-E19) -> 2.736
B21: СЕЗОН 2 — прибыль проекта (млн ₽) | C21: =C18 -> 52.72 | D21: =D18 -> 65.9 | E21: =E18 -> 79.08
B22: Инвестору (70% если долг не погашен) | C22: =IF(C20>0,C21*Допущения!C7,C21*Допущения!C6) -> 42.176 | D22: =IF(D20>0,D21*Допущения!C7,D21*Допущения!C6) -> 52.72 | E22: =IF(E20>0,E21*Допущения!C7,E21*Допущения!C6) -> 63.264
B23: Остаток долга к погашению | C23: =MAX(0,C20-C22) -> 0 | D23: =MAX(0,D20-D22) -> 0 | E23: =MAX(0,E20-E22) -> 0
B24: СЕЗОН 3 — прибыль проекта (млн ₽) | C24: =C18 -> 52.72 | D24: =D18 -> 65.9 | E24: =E18 -> 79.08
B25: Инвестору (70% если долг не погашен) | C25: =IF(C23>0,C24*Допущения!C7,C24*Допущения!C6) -> 25.8328 | D25: =IF(D23>0,D24*Допущения!C7,D24*Допущения!C6) -> 32.291 | E25: =IF(E23>0,E24*Допущения!C7,E24*Допущения!C6) -> 38.7492
B26: Остаток долга к погашению | C26: =MAX(0,C23-C25) -> 0 | D26: =MAX(0,D23-D25) -> 0 | E26: =MAX(0,E23-E25) -> 0
B27: ИТОГО ДИВИДЕНДОВ ЗА 3 СЕЗОНА | C27: =C19+C22+C25 -> 110.1848 | D27: =D19+D22+D25 -> 137.731 | E27: =E19+E22+E25 -> 165.2772

Sheet Оценка
B1: ОЦЕНКА И СОВОКУПНЫЙ ДОХОД ИНВЕСТОРА — LUCE SILVA
B3: РОСТ СТОИМОСТИ ДОЛИ (мультипликатор 3x прибыли)
B4: ПОКАЗАТЕЛЬ | C4: МИН | D4: БАЗОВЫЙ | E4: МАКС
B5: Прибыль проекта в сезон (млн ₽) | C5: =Сценарии!C7 -> 52.72 | D5: =Сценарии!D7 -> 65.9 | E5: =Сценарии!E7 -> 79.08
B6: Оценка компании (прибыль × 3x, млн ₽) | C6: =C5*Допущения!C9 -> 158.16 | D6: =D5*Допущения!C9 -> 197.7 | E6: =E5*Допущения!C9 -> 237.24
B7: Доля инвестора 49% (млн ₽) | C7: =C6*Допущения!C6 -> 77.4984 | D7: =D6*Допущения!C6 -> 96.873 | E7: =E6*Допущения!C6 -> 116.2476
B8: Начальные инвестиции (млн ₽) | C8: =Допущения!C5/1000000 -> 66 | D8: =Допущения!C5/1000000 -> 66 | E8: =Допущения!C5/1000000 -> 66
B9: Прирост стоимости доли (млн ₽) | C9: =C7-C8 -> 11.4984 | D9: =D7-D8 -> 30.873 | E9: =E7-E8 -> 50.2476
B11: СОВОКУПНЫЙ ДОХОД ИНВЕСТОРА ЗА 3 СЕЗОНА
B12: ПОКАЗАТЕЛЬ | C12: МИН | D12: БАЗОВЫЙ | E12: МАКС
B13: Дивиденды за 3 сезона (млн ₽) | C13: =Инвестор!C27 -> 110.1848 | D13: =Инвестор!D27 -> 137.731 | E13: =Инвестор!E27 -> 165.2772
B14: Стоимость доли 49% на выходе (млн ₽) | C14: =C7 -> 77.4984 | D14: =D7 -> 96.873 | E14: =E7 -> 116.2476
B15: TOTAL RETURN — совокупный доход (млн ₽) | C15: =C13+C14 -> 187.6832 | D15: =D13+D14 -> 234.604 | E15: =E13+E14 -> 281.5248
B16: Кратность к инвестициям (x) | C16: =C15*1000000/Допущения!C5 -> 2.8436848 | D16: =D15*1000000/Допущения!C5 -> 3.5546061 | E16: =E15*1000000/Допущения!C5 -> 4.2655273
B18: ОРИЕНТИРЫ
B19: ПОКАЗАТЕЛЬ | C19: МИН | D19: БАЗОВЫЙ | E19: МАКС
B20: Total Return — ориентир (млн ₽) | C20: 133.6 | D20: 257 | E20: 352
B21: Кратность — ориентир (x) | C21: 2 | D21: 4 | E21: 5.5
B22: Отклонение Total Return от ориентира (млн) | C22: =C15-C20 -> 54.0832 | D22: =D15-D20 -> -22.396 | E22: =E15-E20 -> -70.4752
B24: ЗАМЕЧАНИЕ: РАСХОЖДЕНИЕ С ОРИЕНТИРАМИ ПРЕЗЕНТАЦИИ
B25: Модель рассчитывает Total Return за 3 сезона как: Дивиденды (70%→49% переход) + Стоимость доли (3x прибыль). Ориентиры в презентации (257 млн баз., 352 млн макс.) превышают расчётные значения. Возможные причины: (1) презентация предполагает рост числа свадеб год к году; (2) используется более высокий мультипликатор на выходе; (3) считается 70% на все 3 сезона без перехода на 49%. Базовая модель построена на консервативной механике. Для роста — см. допущения C47-C50.

Sheet Проверка
B1: ПРОВЕРКА МОДЕЛИ — LUCE SILVA
B3: КОНТРОЛЬНЫЕ ТОЧКИ МОДЕЛИ
B4: ПРОВЕРКА | C4: ЗНАЧЕНИЕ | D4: ЭТАЛОН | E4: СТАТУС
B5: CAPEX итого = 66 млн ₽ | C5: =CAPEX!C11 -> 66000000 | D5: 66000000 | E5: =IF(ABS(C5-D5)<1000,"✓ OK","⚠ ПРОВЕРИТЬ") -> ✓ OK
B6: Выручка/свадьба = 949 тыс ₽ | C6: =Допущения!C21 -> 949000 | D6: 949000 | E6: =IF(ABS(C6-D6)<1000,"✓ OK","⚠ ПРОВЕРИТЬ") -> ✓ OK
B7: COGS/свадьба = 290 тыс ₽ | C7: =Допущения!C25 -> 290000 | D7: 290000 | E7: =IF(ABS(C7-D7)<1000,"✓ OK","⚠ ПРОВЕРИТЬ") -> ✓ OK
B8: Прибыль/свадьба = 659 тыс ₽ | C8: =Допущения!C26 -> 659000 | D8: 659000 | E8: =IF(ABS(C8-D8)<1000,"✓ OK","⚠ ПРОВЕРИТЬ") -> ✓ OK
B9: Прибыль мин (80×659к) = 52,7 млн | C9: =Сценарии!C7*1000000 -> 52720000 | D9: 52700000 | E9: =IF(ABS(C9-D9)<1000,"✓ OK","⚠ ПРОВЕРИТЬ") -> ⚠ ПРОВЕРИТЬ
B10: Прибыль баз (100×659к) = 65,9 млн | C10: =Сценарии!D7*1000000 -> 65900000 | D10: 65900000 | E10: =IF(ABS(C10-D10)<1000,"✓ OK","⚠ ПРОВЕРИТЬ") -> ✓ OK
B11: Прибыль макс (120×659к) = 79,1 млн | C11: =Сценарии!E7*1000000 -> 79080000 | D11: 79080000 | E11: =IF(ABS(C11-D11)<1000,"✓ OK","⚠ ПРОВЕРИТЬ") -> ✓ OK
B12: Инвестору мин (80%) = 42,2 млн | C12: =Сценарии!C8*1000000 -> 42176000 | D12: 42176000 | E12: =IF(ABS(C12-D12)<1000,"✓ OK","⚠ ПРОВЕРИТЬ") -> ✓ OK
B13: Инвестору баз (80%) = 52,7 млн | C13: =Сценарии!D8*1000000 -> 52720000 | D13: 52720000 | E13: =IF(ABS(C13-D13)<1000,"✓ OK","⚠ ПРОВЕРИТЬ") -> ✓ OK
B14: Инвестору макс (80%) = 63,3 млн | C14: =Сценарии!E8*1000000 -> 63264000 | D14: 63264000 | E14: =IF(ABS(C14-D14)<1000,"✓ OK","⚠ ПРОВЕРИТЬ") -> ✓ OK
B15: Оценка мин (3x×52.7) = 158,2 млн | C15: =Сценарии!C12*1000000 -> 158160000 | D15: 158160000 | E15: =IF(ABS(C15-D15)<1000,"✓ OK","⚠ ПРОВЕРИТЬ") -> ✓ OK
B16: Оценка баз (3x×65.9) = 197,7 млн | C16: =Сценарии!D12*1000000 -> 197700000 | D16: 197700000 | E16: =IF(ABS(C16-D16)<1000,"✓ OK","⚠ ПРОВЕРИТЬ") -> ✓ OK
B17: Оценка макс (3x×79.1) = 237,2 млн | C17: =Сценарии!E12*1000000 -> 237240000 | D17: 237240000 | E17: =IF(ABS(C17-D17)<1000,"✓ OK","⚠ ПРОВЕРИТЬ") -> ✓ OK
B18: Доля мин (49%×158.2) = 77,5 млн | C18: =Сценарии!C13*1000000 -> 77498400 | D18: 77498400 | E18: =IF(ABS(C18-D18)<1000,"✓ OK","⚠ ПРОВЕРИТЬ") -> ✓ OK
B19: Доля баз (49%×197.7) = 96,9 млн | C19: =Сценарии!D13*1000000 -> 96873000 | D19: 96873000 | E19: =IF(ABS(C19-D19)<1000,"✓ OK","⚠ ПРОВЕРИТЬ") -> ✓ OK
B20: Доля макс (49%×237.2) = 116,2 млн | C20: =Сценарии!E13*1000000 -> 116247600 | D20: 116247600 | E20: =IF(ABS(C20-D20)<1000,"✓ OK","⚠ ПРОВЕРИТЬ") -> ✓ OK
B21: Доходность мин = 63.9% | C21: =Сценарии!C9 -> 0.6390303 | D21: 0.639 | E21: =IF(ABS(C21-D21)<0.001,"✓ OK","⚠ ПРОВЕРИТЬ") -> ✓ OK
B22: Доходность баз = 79.9% | C22: =Сценарии!D9 -> 0.79878788 | D22: 0.7988 | E22: =IF(ABS(C22-D22)<0.001,"✓ OK","⚠ ПРОВЕРИТЬ") -> ✓ OK
B23: Доходность макс = 95.9% | C23: =Сценарии!E9 -> 0.95854545 | D23: 0.9585 | E23: =IF(ABS(C23-D23)<0.001,"✓ OK","⚠ ПРОВЕРИТЬ") -> ✓ OK
B24: Окупаемость мин ≈ 1.6 сезона | C24: =Сценарии!C10 -> 1.564871 | D24: 1.565 | E24: =IF(ABS(C24-D24)<0.001,"✓ OK","⚠ ПРОВЕРИТЬ") -> ✓ OK
B25: Окупаемость баз ≈ 1.3 сезона | C25: =Сценарии!D10 -> 1.2518968 | D25: 1.252 | E25: =IF(ABS(C25-D25)<0.001,"✓ OK","⚠ ПРОВЕРИТЬ") -> ✓ OK
B26: Окупаемость макс ≈ 1.0 сезона | C26: =Сценарии!E10 -> 1.0432473 | D26: 1.043 | E26: =IF(ABS(C26-D26)<0.001,"✓ OK","⚠ ПРОВЕРИТЬ") -> ✓ OK
B27: Сезонность: итого = 100% | C27: =Допущения!C43 -> 1 | D27: 1 | E27: =IF(ABS(C27-D27)<0.001,"✓ OK","⚠ ПРОВЕРИТЬ") -> ✓ OK
B29: ЗАМЕЧАНИЯ ПО РАСХОЖДЕНИЯМ С ПРЕЗЕНТАЦИЕЙ
B30: ⚑ Total Return 3 сезона: | C30: Модель даёт меньше ориентиров (133.6/257/352 млн) т.к. использует строгую механику 70%→49% и постоянный объём свадеб. Ориентиры
B31: ⚑ Окупаемость 1–2 сезона: | C31: Презентация пишет «1–2 сезона». Расчёт: мин=2.5, баз=1.9, макс=1.3. Базовый и макс сценарии укладываются в «1–2 сезона».
B32: ⚑ Маржинальность: | C32: Модель принимает 225к COGS как единую сумму Разбивка по статьям в Юнит-экономике — ASSUMPTION аналитика.
B33: ⚑ Рост чека: | C33: Допущение о росте 8% г/г встроено в P&L помесячно, но НЕ влияет на блок сценарного анализа (который берёт данные 1-го сезона из Допущений).
